[
    {
        "content": "營主親切，來者不拒",
        "rating": 5,
        "type": 1,
        "publishedDate": "2024/03/08",
        "tokenization": ""
    },
    {
        "content": "這個是我來過最好的露營區，營主大哥帥氣人又大方！非常值得推薦的露營區！環境維持非常乾淨，廁所浴室都很乾淨，很多細節都處理的很好👍太優質❤️❤️❤️這邊自產自銷的產品非常優秀推推推！山景也漂亮！",
        "rating": 5,
        "type": 1,
        "publishedDate": "2024/01/08",
        "tokenization": ""
    },
    {
        "content": "這裡真的超棒地方便利且風景又美、空氣清新自然老闆也很棒很熱心😍😍😍😍 烤肉也很乾淨下次到南投一定會再來旅遊的好地方，真棒的露營區🏕",
        "rating": 5,
        "type": 1,
        "publishedDate": "2023/11/08",
        "tokenization": ""
    },
    {
        "content": "好山好水 好水質，空氣好，設施完善 廚房冰箱應有盡有，回味少年時的救國團露營時代，點滴在心頭。",
        "rating": 5,
        "type": 1,
        "publishedDate": "2023/10/08",
        "tokenization": ""
    },
    {
        "content": "營主人很客氣，早晚都會巡視和整理環境。附近走路5分鐘就有部落的雜貨店，不怕沒補給品。一個小而巧的營地，5-7帳就滿場了，推家族、朋友包場。",
        "rating": 5,
        "type": 1,
        "publishedDate": "2023/09/08",
        "tokenization": ""
    },
    {
        "content": "環靜清幽，老闆人很好，還會想再來😆 …",
        "rating": 5,
        "type": 1,
        "publishedDate": "2023/06/08",
        "tokenization": ""
    },
    {
        "content": "空氣好 露營⛺️好地方",
        "rating": 5,
        "type": 1,
        "publishedDate": "2023/06/08",
        "tokenization": ""
    },
    {
        "content": "營主很客氣，隨時都會來巡邏但都不會打擾到我們的聚會，默默關心，超貼心的☺️",
        "rating": 5,
        "type": 1,
        "publishedDate": "2023/05/08",
        "tokenization": ""
    },
    {
        "content": "旅人蕉露營區營區小巧不大 , 附近部落有雜貨店可逛逛也有外送早餐可以叫但七帳包場 , 建議要縮到5帳比較剛好就現在大家屬於大帳篷時代七帳太擠還要停車空間 , 真的搭不下營區有提供免費的雨棚公共空間可以使用冰箱與冷凍櫃都可以使用路況好開 , 附近鄰居有點吵",
        "rating": 5,
        "type": 1,
        "publishedDate": "2023/05/08",
        "tokenization": ""
    },
    {
        "content": "推推！",
        "rating": 5,
        "type": 1,
        "publishedDate": "2023/05/08",
        "tokenization": ""
    },
    {
        "content": "很棒的地方，推薦。",
        "rating": 5,
        "type": 1,
        "publishedDate": "2023/05/08",
        "tokenization": ""
    },
    {
        "content": "小而美的露營區，麻雀雖小但五臟俱全。老闆待人熱心隨和，收費部分便宜公道，若花小錢就不要以住飯店高標來評論，這次實際住起來也不像評價所說的那麼糟糕。",
        "rating": 5,
        "type": 1,
        "publishedDate": "2023/05/08",
        "tokenization": ""
    },
    {
        "content": "好營區 適合小團露包區！浴室廁所都很乾淨 水很強又熱！設備齊全 還有室內休息空間可以使用！附近有小商店 東西也滿多的 走路2分鐘可到！還有小溪流可以抓溪蝦魚 走路大概15分鐘會到！",
        "rating": 5,
        "type": 1,
        "publishedDate": "2023/05/08",
        "tokenization": ""
    },
    {
        "content": "美麗動人的風景",
        "rating": 5,
        "type": 1,
        "publishedDate": "2023/05/08",
        "tokenization": ""
    },
    {
        "content": "空氣清新 風景怡人 環境乾凈，營主親切，最佳休閒營地•",
        "rating": 5,
        "type": 1,
        "publishedDate": "2023/05/08",
        "tokenization": ""
    },
    {
        "content": "景色非常的宜人～露營區的老闆和善非常的熱情❤️是一個可放鬆～有回家的感覺好溫暖",
        "rating": 5,
        "type": 1,
        "publishedDate": "2023/05/08",
        "tokenization": ""
    },
    {
        "content": "很棒的露營區喔，特推露友前往。",
        "rating": 5,
        "type": 1,
        "publishedDate": "2023/05/08",
        "tokenization": ""
    },
    {
        "content": "環境清潔風景美麗、老闆親切貼心。",
        "rating": 5,
        "type": 1,
        "publishedDate": "2023/05/08",
        "tokenization": ""
    },
    {
        "content": "老闆很用心經營，露友的建議，都有去改善，老闆也很隨和，",
        "rating": 5,
        "type": 1,
        "publishedDate": "2023/05/08",
        "tokenization": ""
    },
    {
        "content": "舒適翠綠的大片草地帳前即可欣賞山景、與滿天星空",
        "rating": 5,
        "type": 1,
        "publishedDate": "2023/05/08",
        "tokenization": ""
    },
    {
        "content": "環境清幽，老闆服務週到。",
        "rating": 5,
        "type": 1,
        "publishedDate": "2023/05/08",
        "tokenization": ""
    },
    {
        "content": "非常喜歡💕 …",
        "rating": 5,
        "type": 1,
        "publishedDate": "2023/05/08",
        "tokenization": ""
    },
    {
        "content": "炎炎烈日下消暑的好選擇",
        "rating": 5,
        "type": 1,
        "publishedDate": "2023/05/08",
        "tokenization": ""
    },
    {
        "content": "場地整理的很乾淨，四週環山風景優美，老闆服務親切週到。",
        "rating": 5,
        "type": 1,
        "publishedDate": "2023/05/08",
        "tokenization": ""
    },
    {
        "content": "營主親切環境清幽翠綠，蟲鳴鳥叫有如自然之呼喚，又如隱世於塵囂外可放鬆身心，且有適合小孩嬉戲之草坪與戲水池",
        "rating": 5,
        "type": 1,
        "publishedDate": "2023/05/08",
        "tokenization": ""
    },
    {
        "content": "很棒的露營區🏕、適合大人放鬆、小孩奔跑🏃，很推。 …",
        "rating": 5,
        "type": 1,
        "publishedDate": "2023/05/08",
        "tokenization": ""
    },
    {
        "content": "是個很棒的地方",
        "rating": 5,
        "type": 1,
        "publishedDate": "2023/05/08",
        "tokenization": ""
    },
    {
        "content": "生意興隆、好運相隨",
        "rating": 5,
        "type": 1,
        "publishedDate": "2023/05/08",
        "tokenization": ""
    },
    {
        "content": "清流部落［川中島］旅人蕉露營區為世外桃源，可以暫時，拋棄塵囂的紛擾，亦可以追思日據時代，原住先民～賽德克巴萊族人-莫那魯道等英勇事蹟……，營主高先生待客親切，賓至如歸，值得再次探遊。",
        "rating": 5,
        "type": 1,
        "publishedDate": "2023/05/08",
        "tokenization": ""
    },
    {
        "content": "環境優雅，適合4,5個家庭相聚的好地方老闆很隨和",
        "rating": 5,
        "type": 1,
        "publishedDate": "2023/05/08",
        "tokenization": ""
    },
    {
        "content": "露營區環境整體很舒適，老闆人很親切！",
        "rating": 5,
        "type": 1,
        "publishedDate": "2023/05/08",
        "tokenization": ""
    },
    {
        "content": "一片藍天一片一望無際的山眼前這座山彷彿一幅畫讓人心曠神怡是一個放鬆心情的好地方觀賞著日落晚霞紅了半邊天三五好友聊天帶著孩子適合親子郊遊的好地方👍🏻",
        "rating": 5,
        "type": 1,
        "publishedDate": "2023/05/08",
        "tokenization": ""
    },
    {
        "content": "認真有愛的主人，很值得再次感受無價的大自然",
        "rating": 5,
        "type": 1,
        "publishedDate": "2023/05/08",
        "tokenization": ""
    },
    {
        "content": "園區乾淨，方便，清新，價格平民",
        "rating": 5,
        "type": 1,
        "publishedDate": "2023/05/08",
        "tokenization": ""
    },
    {
        "content": "渡假休閒放鬆的好地方~",
        "rating": 5,
        "type": 1,
        "publishedDate": "2023/05/08",
        "tokenization": ""
    },
    {
        "content": "小而五臟俱全的營區七帳就滿帳了都是自己人感覺非常的自在風景很美 田園小路也很愜意營區該有的都有 營主很熱情人很好營主退休後的小本生意下次還會再來🙂",
        "rating": 5,
        "type": 1,
        "publishedDate": "2023/05/08",
        "tokenization": ""
    },
    {
        "content": "「沒有下方評論說的這麼遭」海拔420小營區適合包區，大約6-7帳我們7帳，拉3個天幕沒問題有何師父車貼折扣有冷藏冷凍冷藏在營本部還沒開放營主說因為電壓220水電還沒來處理有小台逆滲透飲水機浴室2間，有附沐浴乳洗髮精水壓大，沒熱水可以自己去後面開廁所3間，蹲1坐2，有附廁紙水桶水漂小便斗2好友一起來露包區很可以不建議散客天幕需共用，無法大家都拉天幕營本部旁邊有室內大空間可使用不用天幕也可以草皮前面和後面是不同的草後方草皮需修剪，太長了前方草皮光腳踩很舒服有護草墊，7帳使用沒問題有吹風機有戲水池，我大人下去水深到大腿大約60公分水難免有雜質，樹葉樹枝那些後方有後門可以自己開門出去那裡有鄉間小路的悠閒感山景很美營主說目前部落限水，可能9月會恢復我們夜衝確實有停水問題大概半夜12點之後就沒水了禮拜六下午也有停水問題停大概一小時左右供水恢復前去露營的露友就注意一下夏天記得防蚊防曬，也有蒼蠅",
        "rating": 5,
        "type": 1,
        "publishedDate": "2023/05/08",
        "tokenization": ""
    },
    {
        "content": "水質差去露營都包區了還自己帶朋友去唱歌，這就算了還一直停水真的可以把露營區關掉了不用去騙錢",
        "rating": 1,
        "type": 1,
        "publishedDate": "2023/05/08",
        "tokenization": ""
    },
    {
        "content": "風景一般環繞山景，水池沒什麼水只到小腿高，水質有點不敢用，晚上9點前要洗完澡，觀感有點不好，知道會停水，是否有個備案能讓露營者方便呢，不然小朋友玩的不盡性，空間一般，但護草墊不足，我們也只墊在睡帳下沒墊其它位置，現在帳篷較多是6人帳起跳的，不要再說，你們帳篷怎那門大，我和另一帳晚到就沒墊了，還碰到下雨，收帳時只能笑一笑了，，老闆這是一般家庭6人帳的，才能睡4人，建議多備一點護草墊。，還有下午有的人習慣睡午覺，但你在隔壁和朋友唱歌，我們一堆人無言，你來打招呼是對我們沒有睡午覺的人來說，你沒見到的都在休息啊老闆，，地方不大啊老闆，我們是包區，但有人要休息啊老闆。附加一下，冰箱目前只有冷凍，沒有冷藏，，，要冷藏要看營本部那台給不給人用，目前不開放，以上僅本人觀點所看。",
        "rating": 2,
        "type": 1,
        "publishedDate": "2023/05/08",
        "tokenization": ""
    },
    {
        "content": "親切營主，小而巧的營區該有的都有。",
        "rating": 5,
        "type": 1,
        "publishedDate": "2023/05/08",
        "tokenization": ""
    }
]