{
    "code": "2372",
    "name": "苗栗南庄 一畝田(蓮花帳)",
    "region": "苗栗縣南庄鄉",
    "url": "https://www.easycamp.com.tw/Store_2372.html",
    "type": 2,
    "disabled": 0,
    "same_name": "一畝田露營區(蓮花帳_狩獵帳)",
    "description": "南庄一畝田，以豪華露營模式，規劃完善設備，讓提供渡假的好選擇豪華露營日加乘多樣玩樂設施，讓你輕鬆圓一個親子露營的夢想天地緊鄰蓬萊溪賞魚步道，到南庄老街也只要 15 分鐘",
    "address": "苗栗縣南庄鄉篷萊村5鄰64-2號",
    "latitude": 24.54375,
    "longitude": 120.973034,
    "comments": [
        {
            "content": "CP值太高了，還想再來~~~",
            "type": 2,
            "rating": 5,
            "publishedDate": "2023/09/25",
            "tokenization": "CP | 值太高 | 還想"
        },
        {
            "content": "營區很乾淨，廁所定時都有人整理",
            "type": 2,
            "rating": 5,
            "publishedDate": "2023/06/30",
            "tokenization": "營區 | 乾淨 | 廁所定 | 時 | 有人 | 整理"
        },
        {
            "content": "對於第一露的全家人是完美的經驗",
            "type": 2,
            "rating": 5,
            "publishedDate": "2023/06/23",
            "tokenization": "第一 | 露 | 全家人 | 完美 | 經驗"
        },
        {
            "content": "露營場地夠大,設施有在保養也還保有乾淨游泳池也夠大,小孩玩得很開心;晚上想要出去覓食也很方便",
            "type": 2,
            "rating": 5,
            "publishedDate": "2023/06/05",
            "tokenization": "露營場 | 地夠 | 設施 | 保養 | 也還 | 保有 | 乾淨 | 游泳池 | 也夠 | 小孩 | 玩得 | 開心 | 晚上 | 想要 | 覓食"
        },
        {
            "content": "很棒 很舒服的露營環境",
            "type": 2,
            "rating": 5,
            "publishedDate": "2023/05/24",
            "tokenization": "很棒 | 舒服 | 露營 | 環境"
        },
        {
            "content": "很平均的營地!。平地的營區，稍熱。希望營主能更仔細清理桌面(油垢)。蓮花帳沒有什麼遮陽效果，一日出就被亮醒了，呵!",
            "type": 2,
            "rating": 5,
            "publishedDate": "2023/04/05",
            "tokenization": "平均 | 營地 | 平地 | 營區 | 稍熱 | 希望 | 營主 | 仔細 | 清理 | 桌面 | 油垢 | 蓮花帳 | 遮陽 | 效果 | 一日 | 亮 | 醒"
        },
        {
            "content": "很值得推薦的營區。很讚，值得來體驗。",
            "type": 2,
            "rating": 5,
            "publishedDate": "2023/03/23",
            "tokenization": "值得 | 推薦 | 營區 | 讚 | 值得 | 體驗"
        },
        {
            "content": "超讚又舒服。廁所都會一直保持著乾淨，讓人很舒服，營主也很好，帶小孩去真的很方便，只需要帶吃的就好。",
            "type": 2,
            "rating": 5,
            "publishedDate": "2023/03/08",
            "tokenization": "超 | 讚 | 舒服 | 廁所 | 著乾淨 | 舒服 | 營主 | 小孩 | 真的 | 吃"
        },
        {
            "content": "非常適合親子露營，設施各部份優良，老闆用心維護、整理，也非常親切健談哦！有機會值得再次遊玩！非常推薦",
            "type": 2,
            "rating": 5,
            "publishedDate": "2023/03/04",
            "tokenization": "適合 | 親子 | 露營 | 設施 | 各部 | 份 | 優良 | 老闆 | 用心 | 維護 | 整理 | 親切 | 健談 | 機會 | 值得 | 遊玩 | 推薦"
        },
        {
            "content": "適合親子，桶仔雞、拔絲地瓜很好吃，人員都很親切。第一次免裝備露營就獻給一畝田了，很適合親子同樂，小孩看到沙坑跟跳跳玩具都很開心，附近還有步道可以散步，營區還有小兔子跟小貓，晚上可以預訂桶仔雞，皮很脆、肉多汁，招待的拔絲地瓜也很好吃",
            "type": 2,
            "rating": 5,
            "publishedDate": "2023/02/21",
            "tokenization": "適合 | 親子 | 桶 | 仔雞 | 拔絲 | 地瓜 | 好吃 | 人員 | 親切 | 第一次 | 免裝備 | 露營 | 獻給 | 一畝 | 田 | 適合 | 親子 | 同樂 | 小孩 | 沙坑 | 跳跳 | 玩具 | 開心 | 還有步 | 道 | 散步 | 營區 | 小兔子 | 小貓 | 晚上 | 預訂 | 桶 | 仔雞 | 皮 | 很脆 | 肉 | 多汁 | 招待 | 拔絲 | 地瓜 | 好吃"
        },
        {
            "content": "舒適的好營區。這次是第四次入住了，還是一樣的放鬆舒適，營主也有聽到建議將桌子的高度降低，揪甘心，也預定暑假了",
            "type": 2,
            "rating": 5,
            "publishedDate": "2023/02/17",
            "tokenization": "舒適 | 營區 | 第四次 | 入住 | 放 | 鬆 | 舒 | 適 | 營主 | 聽 | 建議將 | 桌子 | 高度 | 降低 | 揪 | 甘心 | 預定 | 暑假"
        },
        {
            "content": "值得一去再去。這次是第四次入住了，還是一樣的放鬆舒適，營主也有聽到建議將桌子的高度降低，揪甘心，也預定暑假了",
            "type": 2,
            "rating": 5,
            "publishedDate": "2023/02/17",
            "tokenization": "值得 | 一去 | 第四次 | 入住 | 放 | 鬆 | 舒 | 適 | 營主 | 聽 | 建議將 | 桌子 | 高度 | 降低 | 揪 | 甘心 | 預定 | 暑假"
        },
        {
            "content": "超棒露營地。從自家帶孩子去玩,到邀長輩.朋友一同前往,都能玩的盡興,缺點是越來越難訂到",
            "type": 2,
            "rating": 5,
            "publishedDate": "2023/02/01",
            "tokenization": "超棒露 | 營地 | 孩子 | 玩 | 邀長 | 輩 | 朋友 | 一同 | 前往 | 玩 | 盡興 | 缺點 | 越來 | 越 | 難訂"
        },
        {
            "content": "第一次去免裝備露營 體驗超級好 蓮花帳裡面很大很漂亮營主人也超好 拔絲地瓜超好吃 晚上還看得到流星",
            "type": 2,
            "rating": 5,
            "publishedDate": "2022/12/16",
            "tokenization": "第一次 | 去免 | 裝備 | 露營 | 體驗 | 超級 | 蓮花 | 帳裡面 | 很大 | 很漂亮 | 營主 | 超好 | 拔絲 | 地瓜 | 超 | 好吃 | 晚上 | 還看 | 流星"
        },
        {
            "content": "帶長輩來也住得慣。特地在父親節帶爸爸與孩子一起露營，祖孫三人笑的合不攏嘴，雖然遇上午後陣雨無法玩水，但隔天放晴一樣玩到瘋掉，無奈時間太短。",
            "type": 2,
            "rating": 5,
            "publishedDate": "2022/11/15",
            "tokenization": "帶長 | 輩來 | 住 | 得慣 | 特地 | 父親 | 節帶 | 爸爸 | 孩子 | 露營 | 祖孫三人 | 笑 | 合不攏 | 嘴 | 遇 | 上午 | 陣雨 | 玩水 | 隔天 | 放晴 | 玩 | 瘋 | 掉 | 無奈 | 時間 | 太短"
        },
        {
            "content": "整體服務良好，值得再訪。懶人第二露⛺️想住這種帳篷已久！這次經由家人推薦直接與朋友一起入住結果很滿意",
            "type": 2,
            "rating": 5,
            "publishedDate": "2022/11/13",
            "tokenization": "整體 | 服務 | 值得 | 再訪 | 懶人 | 露 | ⛺ | ️ | 想住 | 帳篷 | 已久 | 經由 | 家人 | 推薦 | 朋友 | 入住 | 滿意"
        },
        {
            "content": "第一次露營 遇到下雨 但小朋友們 玩的還是很開心",
            "type": 2,
            "rating": 5,
            "publishedDate": "2022/11/11",
            "tokenization": "第一次 | 露營 | 下雨 | 小朋友 | 玩 | 開心"
        },
        {
            "content": "很棒的營區。已經入住很3次了，很棒的營區",
            "type": 2,
            "rating": 5,
            "publishedDate": "2022/11/03",
            "tokenization": "很棒 | 營區 | 入住 | 次 | 很棒 | 營區"
        },
        {
            "content": "下次有機會還會想再安排來玩。這是安排的是E區宮庭帳，當天入住時下著雨還好隔天就放晴了。E區旁邊剛好有衛浴跟冰箱方便很多。DIY活動跟遊戲環境非常豐富，小朋友玩的都很開心!",
            "type": 2,
            "rating": 5,
            "publishedDate": "2022/10/24",
            "tokenization": "下次 | 機會 | 還會 | 想 | 安排 | 玩 | 這是 | 安排 | E | 區宮庭帳 | 當天 | 入住 | 時下 | 著雨 | 還好 | 隔天 | 放晴 | E | 區旁邊 | 衛浴 | 冰箱 | DIY | 活動 | 遊戲 | 環境 | 小朋友 | 玩 | 開心"
        },
        {
            "content": "想到出去戶外就會想到這裡，欲罷不能~~~",
            "type": 2,
            "rating": 5,
            "publishedDate": "2022/10/20",
            "tokenization": "想到 | 戶外 | 想到 | 欲罷"
        },
        {
            "content": "很適合夏天帶小孩玩水的地方",
            "type": 2,
            "rating": 4,
            "publishedDate": "2022/10/20",
            "tokenization": "適合 | 夏天 | 小孩 | 玩水 | 地方"
        },
        {
            "content": "環境美,浴廁都很不定時打掃很乾淨,超推",
            "type": 2,
            "rating": 5,
            "publishedDate": "2022/09/26",
            "tokenization": "環境 | 美 | 浴廁 | 時 | 掃 | 乾淨 | 超推"
        },
        {
            "content": "分區完善且營主待人和善親切",
            "type": 2,
            "rating": 5,
            "publishedDate": "2022/09/13",
            "tokenization": "分區 | 完善 | 營主 | 待人 | 和善 | 親切"
        },
        {
            "content": "非常喜歡，適合帶小小孩的好營區",
            "type": 2,
            "rating": 5,
            "publishedDate": "2022/07/29",
            "tokenization": "喜歡 | 適合帶 | 小孩 | 營區"
        },
        {
            "content": "主人很用心。可惜下雨天不然更棒的很棒的景點很好睡",
            "type": 2,
            "rating": 5,
            "publishedDate": "2022/07/24",
            "tokenization": "主人 | 用心 | 可惜 | 下雨天 | 更棒 | 很棒 | 景點 | 睡"
        },
        {
            "content": "帳篷真的很美。帳篷很漂亮 設施很好玩 小孩玩水玩得很開心 有看到螢火蟲 但路上很暗有點恐怖。帳篷廁所都很乾淨 非常棒的回憶跟體驗",
            "type": 2,
            "rating": 5,
            "publishedDate": "2022/07/15",
            "tokenization": "帳篷 | 真的 | 美 | 帳篷 | 很漂亮 | 設施 | 好玩 | 小孩 | 玩水 | 玩得 | 開心 | 螢火蟲 | 路上 | 很暗 | 恐怖 | 帳篷 | 廁所 | 乾淨 | 棒 | 回憶 | 體驗"
        },
        {
            "content": "真是很棒的營區, 已訂好二訪和三訪, 真是孩子的天堂!",
            "type": 2,
            "rating": 5,
            "publishedDate": "2022/06/30",
            "tokenization": "很棒 | 營區 | 已訂 | 好二訪 | 三訪 | 孩子 | 天堂"
        },
        {
            "content": "讚。第二次去，還是感覺很棒",
            "type": 2,
            "rating": 5,
            "publishedDate": "2022/06/28",
            "tokenization": "讚 | 第二次 | 感覺 | 很棒"
        },
        {
            "content": "環境清幽, 有兒童設施, 很適合全家出遊",
            "type": 2,
            "rating": 5,
            "publishedDate": "2022/06/04",
            "tokenization": "環境 | 清幽 | 有兒童 | 設施 | 適合 | 全家 | 出遊"
        },
        {
            "content": "好玩又悠閒的營區，大人小孩都喜歡❤️",
            "type": 2,
            "rating": 5,
            "publishedDate": "2022/05/29",
            "tokenization": "好玩 | 悠閒 | 營區 | 大人 | 小孩 | 喜歡 | ❤ | ️"
        },
        {
            "content": "營主會帶路, 附近可以看到超多螢火蟲, 設施完善並且有在維護。戲水池每日早上會清洗再放乾淨的水, 超棒超適合小小孩的營區!",
            "type": 2,
            "rating": 5,
            "publishedDate": "2022/05/03",
            "tokenization": "營主 | 帶路 | 超多 | 螢火蟲 | 設施 | 完善 | 維護 | 戲 | 水池 | 每日 | 早上 | 清洗 | 再放 | 乾淨 | 水 | 超棒超 | 適合 | 小孩 | 營區"
        },
        {
            "content": "非常方便的露營區，可惜當天下雨，不然更有趣。",
            "type": 2,
            "rating": 5,
            "publishedDate": "2022/03/06",
            "tokenization": "露營區 | 可惜 | 天下 | 雨 | 有趣"
        },
        {
            "content": "五星級營地。很高級且設備完善的營地，有順便訂了桶仔雞和清蒸鱒魚，住的很舒服吃的也很開心，唯一美中不足的就是入住日剛好狂下雨，一定要再選一天好天氣再來一次！營主招待的拔絲地瓜也太好吃了吧！營地雖然不大但還有小動物可以餵，真的蠻不錯的！",
            "type": 2,
            "rating": 5,
            "publishedDate": "2022/02/05",
            "tokenization": "五星 | 級 | 營地 | 高級且 | 設備 | 完善 | 營地 | 有順 | 便訂 | 桶 | 仔雞 | 清蒸 | 鱒魚 | 住 | 舒服 | 吃 | 開心 | 唯一 | 美中不足 | 入住 | 日剛 | 狂 | 下雨 | 選 | 天氣 | 營主 | 招待 | 拔絲 | 地瓜 | 太 | 好吃 | 營地 | 小動物 | 真的 | 蠻不錯"
        },
        {
            "content": "二訪，孩子很喜歡沙坑、餵小白兔及老闆招待的拔絲地瓜！",
            "type": 2,
            "rating": 5,
            "publishedDate": "2022/01/12",
            "tokenization": "二訪 | 孩子 | 喜歡 | 沙坑 | 小白兔 | 老闆 | 招待 | 拔絲 | 地瓜"
        },
        {
            "content": "看得出來營主很用心經營，兩天下來體驗超棒，小小孩也玩得好開心，謝謝營主！。很棒的營區，家裡的小小孩玩沙坑、餵兔子玩得好開心，這裏非常適合親子露營唷！",
            "type": 2,
            "rating": 5,
            "publishedDate": "2021/12/25",
            "tokenization": "看得出 | 營主 | 用心 | 經營 | 兩 | 天下 | 體驗 | 超棒 | 小孩 | 玩 | 開心 | 謝謝 | 營主 | 很棒 | 營區 | 家裡 | 小孩 | 玩 | 沙坑 | 兔子 | 玩得 | 開心 | 裏 | 適合 | 親子 | 露營 | 唷"
        },
        {
            "content": "推薦!環境乾淨!很棒的營地!。首次露營到一畝田真的是選對了，營地環境很乾淨，浴廁水壓大、水也夠熱，還吃到營主招待的拔絲地瓜，好吃!建議下坡路指示露營區域牌的營區名稱可以再標示一下是一畝田的營地，期待下次再到一畝田露營:)",
            "type": 2,
            "rating": 5,
            "publishedDate": "2021/12/05",
            "tokenization": "推薦 | 環境 | 乾淨 | 很棒 | 營地 | 首次 | 露營 | 一畝 | 田 | 真的 | 選 | 營地 | 環境 | 乾淨 | 浴 | 廁水壓 | 水 | 夠熱 | 還吃到 | 營主 | 招待 | 拔絲 | 地瓜 | 好吃 | 建議 | 下坡路 | 指示 | 露營區域 | 牌 | 營區 | 名稱 | 標示 | 一畝 | 田 | 營地 | 期待 | 下次 | 再到 | 一畝 | 田露營"
        },
        {
            "content": "放空、休息的好營區。第二次入住，這次選到宮廷帳，帳篷裡面空間超級大，小孩也是玩到不想睡覺，這次也吃到傳說中的拔絲地瓜，超級好吃，目前已經計畫第三次再去遊玩了！",
            "type": 2,
            "rating": 5,
            "publishedDate": "2021/11/30",
            "tokenization": "放空 | 休息 | 營區 | 第二次 | 入住 | 選到 | 宮廷帳 | 帳篷裡 | 面空間 | 超級 | 小孩 | 玩 | 不想 | 睡覺 | 吃 | 說 | 中 | 拔絲 | 地瓜 | 超級 | 好吃 | 計畫 | 第三次 | 遊玩"
        },
        {
            "content": "超讚的體驗。蓮花帳超美超寬敞，草地有很多設施供孩子跑跳放電，戲水池非常乾淨定期清理，夜間活動親子同樂搗麻糬好吃好玩，營區裡還有一隻超級愛撒嬌的貓，孩子都說太好玩還要再來。",
            "type": 2,
            "rating": 5,
            "publishedDate": "2021/11/29",
            "tokenization": "超 | 讚 | 體 | 驗 | 蓮花帳 | 超美超 | 寬 | 敞 | 草地 | 設施供 | 孩子 | 跑跳 | 放電 | 戲 | 水池 | 乾淨 | 定期 | 清理 | 夜間 | 活動 | 親子 | 同樂 | 搗 | 麻 | 糬 | 好吃 | 好玩 | 營區裡 | 隻 | 超級 | 愛撒嬌 | 的貓 | 孩子 | 說 | 太 | 好玩"
        },
        {
            "content": "漂漂河讓人失望，服務人員態度可再溫和點",
            "type": 2,
            "rating": 4,
            "publishedDate": "2021/10/26",
            "tokenization": "漂 | 漂河 | 失望 | 服務人員 | 態度 | 溫和點"
        },
        {
            "content": "營主很會帶活動。推薦給第一次露營的人",
            "type": 2,
            "rating": 4,
            "publishedDate": "2021/09/20",
            "tokenization": "營主 | 很會 | 活動 | 推薦給 | 第一次 | 露營"
        },
        {
            "content": "很棒的營區。環境好、交通便利、營主親切的營區",
            "type": 2,
            "rating": 5,
            "publishedDate": "2021/09/19",
            "tokenization": "很棒 | 營區 | 環境 | 交通 | 便利 | 營主 | 親切 | 營區"
        },
        {
            "content": "才剛剛回來就讓人想念的營地。  日也美夜也美， 邊玩邊享受美景， 真的是讓人覺得很幸福。  整個營地。才剛剛回來就讓人想念的營地。日也美夜也美，邊玩邊享受美景，真的是讓人覺得很幸福。整個營地環境乾淨，工作人員時不時消毒營地內所有設備，讓客人們玩得很安心。下次還會再造訪。",
            "type": 2,
            "rating": 5,
            "publishedDate": "2021/09/14",
            "tokenization": "剛剛 | 回來 | 想念 | 營地 | 日 | 美夜 | 美 | 邊玩邊 | 享受 | 美景 | 真的 | 人覺 | 幸福 | 營地 | 剛剛 | 回來 | 想念 | 營地 | 日 | 美夜 | 美 | 邊玩邊 | 享受 | 美景 | 真的 | 人覺 | 幸福 | 營地 | 環境 | 乾淨 | 工作 | 人員時 | 消毒 | 營地 | 設備 | 客人 | 玩 | 安心 | 下次 | 還會 | 再造 | 訪"
        },
        {
            "content": "很舒服的營區。只要帶吃的去就好真的很方便",
            "type": 2,
            "rating": 5,
            "publishedDate": "2021/09/04",
            "tokenization": "舒服 | 營區 | 吃 | 真的"
        },
        {
            "content": "超棒的露營體驗，有機會一定會在造訪",
            "type": 2,
            "rating": 5,
            "publishedDate": "2021/08/12",
            "tokenization": "超棒 | 露營 | 體驗 | 機會 | 造訪"
        },
        {
            "content": "服務貼心，像回到家一樣舒服",
            "type": 2,
            "rating": 5,
            "publishedDate": "2021/04/10",
            "tokenization": "服務 | 貼心 | 回到 | 家一樣 | 舒服"
        },
        {
            "content": "交通方便,淋浴大間,熱水大有足,活動多,房內設施齊全!下次還會想去!",
            "type": 2,
            "rating": 5,
            "publishedDate": "2021/03/29",
            "tokenization": "交通 | 淋浴 | 大間 | 熱水大有 | 足 | 活動 | 房內 | 設施 | 齊全 | 下次 | 還會 | 想"
        },
        {
            "content": "豐富好玩活動多多。會再想回去露一次的營地，要搶位啊~棒棒",
            "type": 2,
            "rating": 5,
            "publishedDate": "2021/03/14",
            "tokenization": "好玩 | 活動 | 想 | 回去 | 露 | 營地 | 搶位 | 棒棒"
        },
        {
            "content": "營主很用心，就算是星期日晚上也帶了我們搗麻糬，還放了煙火，大人小孩都非常開心呢！。那個椅子可以都一樣嗎？我們那天的白色椅子，椅子的布一直掉下去，謝謝喔！",
            "type": 2,
            "rating": 4,
            "publishedDate": "2021/03/06",
            "tokenization": "營主 | 用心 | 星期日 | 晚上 | 搗 | 麻 | 糬 | 還放 | 煙火 | 大人 | 小孩 | 開心 | 椅子 | 那天 | 白色 | 椅子 | 椅子 | 布 | 掉下去 | 謝謝 | 喔"
        },
        {
            "content": "營區維護的很好、浴廁環境也乾淨、營區內的設施很適合家裡有小朋友的家庭、還有搗麻糬跟棉花糖...等等。。會再訪的營區！",
            "type": 2,
            "rating": 5,
            "publishedDate": "2021/02/21",
            "tokenization": "營區 | 維護 | 浴廁 | 環境 | 乾淨 | 營區 | 設施 | 很適 | 合家 | 裡有 | 小朋友 | 家庭 | 搗 | 麻 | 糬 | 棉花 | 糖 | 再訪 | 營區"
        },
        {
            "content": "交通方便，營區乾淨。營區一直聞到煙味，不知道營區是否有禁止吸煙? 但營友們多數是一家大小來露營，還有很多小小孩，還是希望若能多多宣導請勿吸煙，這樣營區就更完美了！",
            "type": 2,
            "rating": 4,
            "publishedDate": "2021/02/14",
            "tokenization": "交通 | 營區 | 乾淨 | 營區 | 聞到 | 煙味 | 營區 | 禁止 | 吸煙 | 營友們 | 一家 | 大小 | 露營 | 小孩 | 希望 | 若能 | 宣導 | 請 | 勿 | 吸煙 | 營區 | 完美"
        },
        {
            "content": "讚。環境乾淨又美,小孩子都玩得很開心下回一定再到訪",
            "type": 2,
            "rating": 5,
            "publishedDate": "2021/01/05",
            "tokenization": "讚 | 環境 | 乾淨 | 美 | 小孩子 | 玩 | 開心 | 下回 | 訪"
        },
        {
            "content": "親子友善營區。感謝營區提供動物飼料可以餵食小動物，小孩都餵的很開心漂漂河水非常清涼，泡腳消暑很舒服唯獨營區蜜蜂太多，雖然不傷人，但還是很害怕，因為會一直在身邊飛舞，希望營主可以找尋一下蜂窩在哪，請消防人員協助摘除",
            "type": 2,
            "rating": 5,
            "publishedDate": "2020/11/13",
            "tokenization": "親子 | 友善 | 營區 | 感謝 | 營區 | 提供 | 動物 | 飼料 | 食小動物 | 小孩 | 開心 | 漂漂 | 河水 | 清涼 | 泡腳 | 消暑 | 舒服 | 唯獨 | 營區 | 蜜蜂 | 太 | 不傷 | 害怕 | 因為 | 身邊 | 飛舞 | 希望 | 營主 | 找尋 | 蜂窩 | 請 | 消防人 | 員協助 | 摘除"
        },
        {
            "content": "營區採人車分道，有小動物區適合親子",
            "type": 2,
            "rating": 5,
            "publishedDate": "2020/11/12",
            "tokenization": "營區 | 採人車 | 分道 | 有小動 | 物區 | 適合 | 親子"
        },
        {
            "content": "草地維護不錯，夜間有搗麻糬活動很棒",
            "type": 2,
            "rating": 5,
            "publishedDate": "2020/11/12",
            "tokenization": "草地 | 維護 | 不錯 | 夜間 | 搗 | 麻 | 糬 | 動 | 很棒"
        },
        {
            "content": "各自帳篷空間間距大，相當舒服！。廁所跟淋浴因為燈光吸引許多小蟲子，建議上方可以做個隔板擋住，不然洗到一半突然小昆蟲跑進來，真的不知該跑不該跑～～哈哈哈～～",
            "type": 2,
            "rating": 5,
            "publishedDate": "2020/08/12",
            "tokenization": "帳篷 | 空間 | 間 | 舒服 | 廁所 | 淋浴 | 因為 | 燈光 | 吸引 | 小蟲子 | 建議 | 上方 | 做個 | 隔板 | 擋 | 住 | 洗 | 一半 | 小昆蟲 | 跑 | 真的 | 不知 | 跑 | 跑 | 哈哈哈"
        },
        {
            "content": "會再訪的營區。營主很盡責的在管制，給予露友相當的露營品質。每一區都有自己的沙坑跟鞦韆，很貼心！！戲水池的的溜滑梯深受小孩喜愛，但飄飄河有點滑，小孩有滑倒幾次..24小時的熱水供應不用在尖峰時期人擠人，收搭完滿身汗也能隨時洗個澡保持舒爽！整體是很不錯的營區，會再訪的！",
            "type": 2,
            "rating": 5,
            "publishedDate": "2020/08/04",
            "tokenization": "再訪 | 營區 | 營主 | 盡責 | 管制 | 給予 | 露友 | 露營 | 品質 | 每一區 | 沙坑 | 鞦 | 韆 | 貼心 | 戲 | 水池 | 溜滑梯 | 深受 | 小孩 | 喜愛 | 飄飄河 | 滑 | 小孩 | 滑倒 | 幾次 | 24 | 小時 | 熱水供 | 應 | 不用 | 尖峰 | 時期 | 擠 | 收 | 搭 | 完滿 | 身汗 | 洗個 | 澡 | 舒爽 | 整體 | 不錯 | 營區 | 再訪"
        },
        {
            "content": "親子適合露營區。小包區很棒，在漂漂河旁邊，泳池有小小溜滑梯，也可以點甕仔雞，省去晚餐辛苦煮菜",
            "type": 2,
            "rating": 5,
            "publishedDate": "2020/07/29",
            "tokenization": "親子 | 適合露 | 營區 | 小包 | 區 | 很棒 | 漂 | 漂河 | 旁邊 | 泳池 | 小小 | 溜滑梯 | 點甕仔雞 | 省去 | 晚餐 | 辛苦 | 煮菜"
        },
        {
            "content": "很用心。D區草原很舒適，漂漂河最棒了,小動物也很有趣, 草地遇到下雨排水也還可以。",
            "type": 2,
            "rating": 5,
            "publishedDate": "2020/06/19",
            "tokenization": "用心 | D | 區 | 草原 | 很舒適 | 漂 | 漂河 | 最棒 | 小動物 | 有趣 | 草地 | 下雨 | 排水 | 也還"
        },
        {
            "content": "環境不錯只是小黑蚊有點多",
            "type": 2,
            "rating": 5,
            "publishedDate": "2020/03/29",
            "tokenization": "環境 | 不錯 | 小黑 | 蚊有點"
        },
        {
            "content": "熱心的營主。感謝臨時租借我們客廳帳免濕帳收場",
            "type": 2,
            "rating": 4,
            "publishedDate": "2020/03/16",
            "tokenization": "熱心 | 營主 | 感謝 | 臨時 | 租借 | 客廳 | 帳免 | 濕帳 | 收場"
        },
        {
            "content": "營主安排搗麻糬，棉花糖及豆花DIY活動。很充實，大小孩都愛。",
            "type": 2,
            "rating": 5,
            "publishedDate": "2020/03/15",
            "tokenization": "營主 | 安排 | 搗 | 麻 | 糬 | 棉花 | 糖及 | 豆花 | DIY | 活動 | 充實 | 小孩 | 愛"
        },
        {
            "content": "很適合帶小孩子去的營地",
            "type": 2,
            "rating": 5,
            "publishedDate": "2020/03/02",
            "tokenization": "適合帶 | 小孩子 | 營地"
        },
        {
            "content": "好玩美麗的營區。親切服務 小孩可以消耗體力 唯一風太大 隔壁帳直接客廳吹翻 活動很多 有棉花糖DIY 煙火 搗麻糬 小動物 值得回露",
            "type": 2,
            "rating": 5,
            "publishedDate": "2020/02/10",
            "tokenization": "好玩 | 美麗 | 營區 | 親切 | 服務 | 小孩 | 消耗 | 體力 | 唯一 | 風太大 | 隔壁 | 帳 | 客廳 | 吹 | 翻 | 活動 | 棉花 | 糖 | DIY | 煙火 | 搗 | 麻 | 糬 | 小動物 | 值得 | 回露"
        },
        {
            "content": "很適合帶小孩去的營區，小孩去都玩瘋了",
            "type": 2,
            "rating": 5,
            "publishedDate": "2020/01/08",
            "tokenization": "適合帶 | 小孩 | 營區 | 小孩 | 玩 | 瘋"
        },
        {
            "content": "非常用心的營區，環境非常優，帳篷搭完，仍能有足夠的空間可以讓孩子們玩耍。",
            "type": 2,
            "rating": 5,
            "publishedDate": "2020/01/03",
            "tokenization": "用心 | 營區 | 環境 | 優 | 帳篷 | 搭 | 完 | 仍能 | 足夠 | 空間 | 孩子 | 玩耍"
        },
        {
            "content": "遊樂設施豐富~衛浴乾淨~草皮豐厚~很讚!",
            "type": 2,
            "rating": 5,
            "publishedDate": "2019/12/24",
            "tokenization": "遊樂 | 設施 | 衛浴 | 乾淨 | 草皮 | 豐厚 | 讚"
        },
        {
            "content": "很不錯的營區~還有搗麻糬跟放煙火的活動!",
            "type": 2,
            "rating": 5,
            "publishedDate": "2019/12/24",
            "tokenization": "很不錯 | 營區 | 搗 | 麻 | 糬 | 放 | 煙 | 火 | 動"
        },
        {
            "content": "親子營地很棒。園內很多小孩可以玩的設施，十分適合親子露營",
            "type": 2,
            "rating": 5,
            "publishedDate": "2019/12/08",
            "tokenization": "親子 | 營地 | 很棒 | 園內 | 小孩 | 玩 | 設施 | 適合 | 親子 | 露營"
        },
        {
            "content": "非常適合親子的露營區，玩水+餵小兔子就讓小孩玩的很開心",
            "type": 2,
            "rating": 5,
            "publishedDate": "2019/09/16",
            "tokenization": "適合 | 親子 | 露營區 | 玩水 | 小兔子 | 小孩 | 玩 | 開心"
        },
        {
            "content": "經營很用心，活動很多，極棒營地。",
            "type": 2,
            "rating": 5,
            "publishedDate": "2019/09/03",
            "tokenization": "經營 | 用心 | 活動 | 極棒營"
        },
        {
            "content": "交通便利，營區舒適，孩子玩得開心，很棒！",
            "type": 2,
            "rating": 5,
            "publishedDate": "2019/08/20",
            "tokenization": "交通 | 便利 | 營區 | 舒適 | 孩子 | 玩得 | 開心 | 很棒"
        },
        {
            "content": "營區寬敞舒服～戲水區大人小孩都玩瘋了！營主熱情好客，讓第一次露營的我們有美好的回憶！",
            "type": 2,
            "rating": 5,
            "publishedDate": "2019/07/29",
            "tokenization": "營區 | 寬 | 敞 | 舒服 | 戲水區 | 大人 | 小孩 | 玩 | 瘋 | 營主 | 熱情 | 好客 | 第一次 | 露營 | 美好 | 回憶"
        },
        {
            "content": "活動豐富，設施多樣，營主有在用心管理，非常值得推薦～",
            "type": 2,
            "rating": 5,
            "publishedDate": "2019/07/29",
            "tokenization": "活動 | 設施 | 多樣 | 營主 | 用心 | 管理 | 值得 | 推薦"
        },
        {
            "content": "兩個字「超棒！」。營主熱情用心的招待每個營位自製各式小點心，還有心花朵朵開的DIY棉花糖體驗，完全收買大人小孩。環境清潔管理做的很棒，餵養兔兔區也乾淨。玩水區更是早晚清理，用心真的看的見。",
            "type": 2,
            "rating": 5,
            "publishedDate": "2019/07/27",
            "tokenization": "兩個 | 字 | 超棒 | 營主 | 熱情 | 用心 | 招待 | 營位 | 製 | 小點心 | 有心 | 花朵 | 朵 | 開 | DIY | 棉花 | 糖體驗 | 收買 | 大人 | 小孩 | 環境 | 清潔 | 管理 | 做 | 很棒 | 餵養 | 兔 | 兔區 | 乾淨 | 玩水 | 區 | 更是 | 早晚 | 清理 | 用心 | 真的"
        },
        {
            "content": "營區活動多，搗麻糬、放煙火、棉花糖、是個值得再訪的營區",
            "type": 2,
            "rating": 5,
            "publishedDate": "2019/06/25",
            "tokenization": "營區 | 活動 | 搗 | 麻 | 糬 | 放煙火 | 棉花 | 糖 | 值得 | 再訪 | 營區"
        },
        {
            "content": "營主人很好，反應的狀況會迅速幫忙解決",
            "type": 2,
            "rating": 5,
            "publishedDate": "2019/06/21",
            "tokenization": "營主 | 狀況 | 幫忙 | 解決"
        },
        {
            "content": "很棒的親子營地，設施齊全，老闆親切，值得再訪!",
            "type": 2,
            "rating": 5,
            "publishedDate": "2019/06/21",
            "tokenization": "很棒 | 親子 | 營地 | 設施 | 齊全 | 老闆 | 親切 | 值得 | 再訪"
        },
        {
            "content": "營區的整體規劃不錯，有多項兒童遊樂設施，綠化..繡球花開得很美，且營位不擁擠，衛浴乾淨，很棒!",
            "type": 2,
            "rating": 5,
            "publishedDate": "2019/06/21",
            "tokenization": "營區 | 整體 | 規劃 | 不錯 | 項兒 | 童遊樂 | 設施 | 綠化 | 繡 | 球花 | 開得 | 美 | 營位 | 擁擠 | 衛浴 | 乾淨 | 很棒"
        },
        {
            "content": "營區很用心的舉辦多項活動，搗麻糬、放煙火、棉花糖、餵小兔子，讓露營更有趣精彩，是個值得再訪的營區!",
            "type": 2,
            "rating": 5,
            "publishedDate": "2019/06/21",
            "tokenization": "營區 | 用心 | 舉辦 | 多項 | 活動 | 搗 | 麻 | 糬 | 放煙火 | 棉花 | 糖 | 小兔子 | 露營 | 有趣 | 精彩 | 值得 | 再訪 | 營區"
        },
        {
            "content": "值得再來的好營區。營主很友善熱情，營區也有數個親子活動。遊樂設施足夠，帳位也夠大，一定會再來的好營區。",
            "type": 2,
            "rating": 5,
            "publishedDate": "2019/06/03",
            "tokenization": "值得 | 再來 | 營區 | 營主 | 友善 | 熱情 | 營區 | 數個 | 親子 | 活動 | 遊樂 | 設施 | 足夠 | 帳位 | 也夠 | 營區"
        },
        {
            "content": "很舒服的營區，小孩玩得很開心",
            "type": 2,
            "rating": 5,
            "publishedDate": "2019/04/06",
            "tokenization": "舒服 | 營區 | 小孩 | 玩得 | 開心"
        },
        {
            "content": "很用心的營主。B區比想像中大很多，只收四帳空間很大，不會帳帳相連很舒適的間距。環境乾淨衛生，營主很用心舉辦許多活動讓露營增添精彩，搗麻糬前還會放煙火，環境綠化的很美。營主還到處廣播時間提醒讓大家不會錯過麻糬活動，也會在10點廣播提醒降低音量，很可惜一些露友還是讓孩子到處喧嘩奔跑。很棒的營區納入口袋名單。",
            "type": 2,
            "rating": 5,
            "publishedDate": "2019/03/31",
            "tokenization": "用心 | 營主 | B | 區比 | 想像中 | 收四帳 | 空間 | 很大 | 帳帳 | 相連 | 舒適 | 間 | 環境 | 乾淨衛生 | 營主 | 用心 | 舉辦 | 活動 | 露營 | 增添 | 精彩 | 搗 | 麻 | 糬 | 前 | 放 | 煙 | 火 | 環境 | 綠化 | 美 | 營主 | 還到 | 處廣播 | 時間 | 提醒 | 錯過 | 麻 | 糬 | 動 | 10 | 點廣播 | 提醒 | 降低 | 音量 | 可惜 | 露友 | 孩子 | 處 | 喧嘩 | 奔跑 | 很棒 | 營區 | 納入 | 口袋 | 名單"
        },
        {
            "content": "營區很棒。。他區露客10點過後品酒大會開心聊天到半夜1點，全然不顧其他人睡眠品質，我從10點被吵得到1點後才入睡，建議營主除了10點的廣播之外，可以增加1-2次巡視/勸導頻率。",
            "type": 2,
            "rating": 5,
            "publishedDate": "2019/03/31",
            "tokenization": "營區 | 很棒 | 他區 | 露客 | 10 | 點過 | 品酒 | 大會 | 開心 | 聊天 | 半夜 | 點 | 不顧 | 其他人 | 睡眠 | 品質 | 10 | 點被 | 吵 | 點後才 | 入睡 | 建議 | 營主 | 10 | 點的 | 廣播 | 之外 | 增加 | 次 | 巡視 | 勸導 | 頻率"
        },
        {
            "content": "看的出營主很用心在經營～很適合小朋友的一個營區～（附近學校旁的餐館真的是難吃到爆炸，超級地雷～）",
            "type": 2,
            "rating": 5,
            "publishedDate": "2019/03/31",
            "tokenization": "營主 | 用心 | 經營 | 適合 | 小朋友 | 營區 | 學校 | 旁 | 餐館 | 真的 | 難 | 吃 | 爆炸 | 超級 | 地雷"
        },
        {
            "content": "景色優美，值得再訪。起床眼前就是雲霧飄渺，很棒可惜下雨，一些設施都不能玩",
            "type": 2,
            "rating": 5,
            "publishedDate": "2019/03/26",
            "tokenization": "景色 | 優美 | 值得 | 再訪 | 起床 | 眼前 | 雲霧 | 飄渺 | 很棒 | 可惜 | 下雨 | 設施 | 玩"
        },
        {
            "content": "搗麻糬和棉花糖活動很加分",
            "type": 2,
            "rating": 5,
            "publishedDate": "2019/03/05",
            "tokenization": "搗 | 麻 | 糬 | 棉花 | 糖 | 活動 | 加分"
        },
        {
            "content": "超棒的營地，路況佳，適合小孩的親子營地",
            "type": 2,
            "rating": 5,
            "publishedDate": "2019/03/03",
            "tokenization": "超棒 | 營地 | 路況 | 佳 | 適合 | 小孩 | 親子 | 營地"
        },
        {
            "content": "景色不錯，環境乾淨，草坪厚實，沒什麼蚊蟲，晚上有免費搗麻糬活動，白天有棉花糖DIY。",
            "type": 2,
            "rating": 5,
            "publishedDate": "2019/03/03",
            "tokenization": "景色 | 不錯 | 環境 | 乾淨 | 草坪 | 厚實 | 沒什麼 | 蚊蟲 | 晚上 | 免費 | 搗 | 麻 | 糬 | 動 | 白天 | 棉花 | 糖 | DIY"
        },
        {
            "content": "希望貴營區管制抽煙露客。抽煙露客太多，對於親子露客相當困擾，這麼棒的營地不能讓大家好好呼吸非常可惜！",
            "type": 2,
            "rating": 5,
            "publishedDate": "2019/03/03",
            "tokenization": "希望 | 貴營區 | 管制 | 抽煙 | 露客 | 抽煙露 | 客太多 | 親子 | 露客 | 困擾 | 棒 | 營地 | 好好 | 呼吸 | 可惜"
        },
        {
            "content": "有厚草皮孩子可盡情的玩.一早起來有棉花糖讓孩子們很驚喜",
            "type": 2,
            "rating": 4,
            "publishedDate": "2019/02/17",
            "tokenization": "有厚 | 草皮 | 孩子 | 可盡情 | 玩 | 一早 | 棉花 | 糖 | 孩子 | 驚喜"
        },
        {
            "content": "營地很乾淨 營主很用心辦很多活動。棒！",
            "type": 2,
            "rating": 5,
            "publishedDate": "2019/02/12",
            "tokenization": "營地 | 乾淨 | 營主 | 用心 | 辦 | 活動 | 棒"
        },
        {
            "content": "環境清幽，營主熱情，服務很好",
            "type": 2,
            "rating": 5,
            "publishedDate": "2019/02/11",
            "tokenization": "環境 | 清幽 | 營主 | 熱情 | 服務"
        },
        {
            "content": "非常適合親子共遊的營地，滿帳也不至於擁擠，浴室熱水強又穩，也維持的很乾淨",
            "type": 2,
            "rating": 5,
            "publishedDate": "2019/02/10",
            "tokenization": "適合 | 親子 | 共遊 | 營地 | 滿帳 | 擁擠 | 浴室 | 熱水強 | 穩 | 乾淨"
        },
        {
            "content": "營區內有些可愛的小造景，增添不少驚喜。裡面的遊樂設施，孩子也玩得不亦樂乎，還吃到營主自製的棉花糖，讚",
            "type": 2,
            "rating": 4,
            "publishedDate": "2019/02/10",
            "tokenization": "營區 | 可愛的 | 造景 | 增添 | 驚喜 | 遊樂 | 設施 | 孩子 | 玩 | 還吃到 | 營主 | 製 | 棉花 | 糖 | 讚"
        },
        {
            "content": "老闆很有心，晚上準備了搗麻糬體驗，有沙坑鞦韆還有小動物，是一個非常適合親子的營地~。唯一美中不足的是，我們有訂烤雞，但老闆送錯給其他遊客，導致多等了一個小時，而老闆事後處理的態度誠懇，讓我們感到滿意，烤雞很好吃，非常推薦!!!!",
            "type": 2,
            "rating": 5,
            "publishedDate": "2019/02/09",
            "tokenization": "老闆 | 有心 | 晚上 | 搗 | 麻 | 糬 | 體 | 驗 | 沙坑 | 鞦 | 韆 | 動 | 物 | 適合 | 親子 | 營地 | 唯一 | 美中不足 | 有訂 | 烤 | 雞 | 老闆 | 送 | 錯給 | 遊客 | 導致 | 小時 | 老闆 | 事後處理 | 態度 | 誠懇 | 感到 | 滿意 | 烤 | 雞 | 好吃 | 推薦"
        },
        {
            "content": "風景不錯，也沒有小黑蚊和蒼蠅，營地也很寬敞。浴室冷熱水不太好控制",
            "type": 2,
            "rating": 5,
            "publishedDate": "2019/02/09",
            "tokenization": "風景 | 不錯 | 小黑 | 蚊 | 蒼蠅 | 營地 | 寬 | 敞 | 浴室 | 冷熱水 | 不太好 | 控制"
        },
        {
            "content": "熱情的營主，很讚的場地，大人小孩都開心，下次一定再來，超推薦！",
            "type": 2,
            "rating": 5,
            "publishedDate": "2019/02/09",
            "tokenization": "熱情 | 營主 | 讚 | 場 | 大人 | 小孩 | 開心 | 下次 | 再來 | 超推薦"
        },
        {
            "content": "非常宜人的營地，假日還有辦團體活動，好。衛浴設備環境可以加強",
            "type": 2,
            "rating": 5,
            "publishedDate": "2019/02/09",
            "tokenization": "宜人 | 營地 | 假日 | 辦團體 | 活動 | 衛浴 | 設備 | 環境"
        },
        {
            "content": "營主熱情大方，活動很多很適合小孩，是很棒的露營體驗，超讚！",
            "type": 2,
            "rating": 5,
            "publishedDate": "2019/02/08",
            "tokenization": "營主 | 熱情 | 大方 | 活動 | 適合 | 小孩 | 很棒 | 露營 | 體驗 | 超 | 讚"
        },
        {
            "content": "老闆很親切，是一個非常棒的營區",
            "type": 2,
            "rating": 5,
            "publishedDate": "2019/02/05",
            "tokenization": "老闆 | 親切 | 棒 | 營區"
        },
        {
            "content": "環境幽靜老闆熱情。老闆看我們環境太暗還主動借我們燈條，還請我們吃拔絲地瓜，熱熱甜甜，香脆好吃，比餐廳點的還美味。還介紹我們去附近溪流健行，滿滿的魚兒～很好的體驗。",
            "type": 2,
            "rating": 5,
            "publishedDate": "2019/02/04",
            "tokenization": "環境 | 幽靜 | 老闆 | 熱情 | 老闆 | 環境 | 太暗 | 還主動 | 燈條 | 還請 | 吃 | 拔絲 | 地瓜 | 熱熱 | 甜甜 | 香脆 | 好吃 | 比餐 | 廳 | 點的還 | 美味 | 還介紹 | 溪流 | 健行 | 滿滿 | 魚兒 | 體驗"
        },
        {
            "content": "平日包場空間超大，雖沒體驗到營區的搗麻糬和棉花糖，但孩子們放電的很徹底，老闆招待的拔絲地瓜超好吃",
            "type": 2,
            "rating": 5,
            "publishedDate": "2019/02/04",
            "tokenization": "平日 | 包場 | 空間 | 超大 | 沒體驗 | 營區 | 搗 | 麻 | 糬 | 棉花 | 糖 | 孩子 | 放電 | 老闆 | 招待 | 拔絲 | 地瓜 | 超 | 好吃"
        },
        {
            "content": "少有的營主與露友戶動的親子露營區，真的讚",
            "type": 2,
            "rating": 5,
            "publishedDate": "2019/02/03",
            "tokenization": "少有 | 營主 | 露友 | 戶動 | 親子 | 露營區 | 真的 | 讚"
        },
        {
            "content": "活動多，整個營區很用心在經營跟美化環境，讓人覺得舒服。。有機會再造訪，希望能看到更多的多肉植物，謝謝老闆真心招待的拔絲地瓜，真的不愧是招牌甜點",
            "type": 2,
            "rating": 5,
            "publishedDate": "2019/01/28",
            "tokenization": "活動 | 營區 | 用心 | 經營 | 美化 | 環境 | 人覺 | 舒服 | 機會 | 再造 | 訪 | 希望 | 肉 | 植物 | 謝謝 | 老闆 | 真心 | 招待 | 拔絲 | 地瓜 | 真的 | 不愧 | 招牌 | 甜點"
        },
        {
            "content": "自己搗麻糬吃，真的很特別，謝謝特別指名~。超貼心的營地，不是特別的假日夜晚仍有煙火可欣賞;且晚上有搗麻糬，早上有棉花糖DIY,超適合親子露營!",
            "type": 2,
            "rating": 5,
            "publishedDate": "2019/01/27",
            "tokenization": "搗 | 麻 | 糬 | 吃 | 真的 | 很特別 | 謝謝 | 特別 | 指名 | 超貼 | 心 | 營地 | 特別 | 假日 | 夜晚 | 仍有 | 煙火 | 可欣賞 | 晚上 | 搗 | 麻 | 糬 | 早上 | 棉花 | 糖 | DIY | 超適合 | 親子 | 露營"
        },
        {
            "content": "很棒的親子露營區。小朋友的歡樂聲從早到晚不絕於耳，還有免費的搗麻糬和棉花糖DIY，值得體驗。",
            "type": 2,
            "rating": 5,
            "publishedDate": "2019/01/27",
            "tokenization": "很棒 | 親子 | 露營區 | 小朋友 | 歡樂聲 | 早到 | 晚不絕 | 耳 | 免費 | 搗 | 麻 | 糬 | 棉花 | 糖 | DIY | 值得 | 體驗"
        },
        {
            "content": "溜小孩的好地方，有搗麻吉還活動、有放煙火，又有手作棉花糖",
            "type": 2,
            "rating": 5,
            "publishedDate": "2019/01/27",
            "tokenization": "溜 | 小孩 | 地方 | 搗 | 麻吉還 | 活動 | 有放煙火 | 手作 | 棉花 | 糖"
        },
        {
            "content": "值得推薦的親子營區。路好走，位置給的很大，搭滿帳都不覺得擠，廁所乾淨，遊戲區很讚～小孩玩到都不知道要回來～烤雞真的很好吃～有去的露友ㄧ定要嚐嚐～重點營主人超好的～",
            "type": 2,
            "rating": 5,
            "publishedDate": "2019/01/21",
            "tokenization": "值得 | 推薦 | 親子 | 營區 | 路 | 走 | 位置 | 給的 | 很大 | 搭滿帳 | 不覺 | 擠 | 廁所 | 乾淨 | 遊戲區 | 讚 | 小孩 | 玩到 | 回來 | 烤 | 雞 | 真的 | 好吃 | 露友 | ㄧ | 嚐嚐 | 重點 | 營主 | 人超"
        },
        {
            "content": "營主很用心，安排的搗麻糬活動跟棉花糖DIY，小朋友非常喜歡，謝謝招待",
            "type": 2,
            "rating": 5,
            "publishedDate": "2019/01/13",
            "tokenization": "營主 | 用心 | 安排 | 搗 | 麻 | 糬 | 動 | 棉花 | 糖 | DIY | 小朋友 | 喜歡 | 謝謝 | 招待"
        },
        {
            "content": "優良的營區!。路況好，設施佳，活動多，小孩子玩的盡興!",
            "type": 2,
            "rating": 5,
            "publishedDate": "2019/01/13",
            "tokenization": "優良 | 營區 | 路況 | 設施佳 | 活動 | 小孩子 | 玩 | 盡興"
        },
        {
            "content": "謝謝營主的用心 讓我們ㄧ家都玩得開心",
            "type": 2,
            "rating": 5,
            "publishedDate": "2019/01/13",
            "tokenization": "謝謝 | 營主 | 用心 | ㄧ | 家 | 玩 | 開心"
        },
        {
            "content": "真的很棒的營地 會列入再訪的地方",
            "type": 2,
            "rating": 5,
            "publishedDate": "2019/01/04",
            "tokenization": "真的 | 很棒 | 營地 | 列入 | 再訪 | 地方"
        },
        {
            "content": "很棒的親子營地，有搗麻糬，餵食兔子，做棉花糖等活動，營主熱心服務",
            "type": 2,
            "rating": 5,
            "publishedDate": "2018/12/31",
            "tokenization": "很棒 | 親子 | 營地 | 搗 | 麻 | 糬 | 餵食 | 兔子 | 做 | 棉花 | 糖 | 活動 | 營主 | 熱 | 心服 | 務"
        },
        {
            "content": "小朋友玩的很開心 設施很完善",
            "type": 2,
            "rating": 5,
            "publishedDate": "2018/12/31",
            "tokenization": "小朋友 | 玩 | 開心 | 設施 | 完善"
        },
        {
            "content": "營主，很親切很有用心在經營，有空再去。沒啥好建議的",
            "type": 2,
            "rating": 5,
            "publishedDate": "2018/12/30",
            "tokenization": "營主 | 親切 | 用心 | 經營 | 有空 | 建議"
        },
        {
            "content": "狩獵帳非常舒服，設施讓小孩整個不能自己，大推！",
            "type": 2,
            "rating": 5,
            "publishedDate": "2018/12/30",
            "tokenization": "狩獵帳 | 舒服 | 設施 | 小孩 | 不能自己 | 推"
        },
        {
            "content": "感謝老闆用心的安排小活動~。活動用心，謝謝",
            "type": 2,
            "rating": 4,
            "publishedDate": "2018/12/26",
            "tokenization": "感謝 | 老闆 | 用心 | 安排 | 小活動 | 活動 | 用心 | 謝謝"
        },
        {
            "content": "營主熱情活動也多，是個很棒的營區。營主熱情又親切，夜間煙火及搗麻糬活動很好玩，使得整營區歡笑聲不斷。熱水量很大很穩，只可惜有一兩隻超大蜜蜂一直飛來飛去，搞得整家人心惶惶，雖然營主也很熱心幫忙捕捉，但還是很害怕。滿帳時小孩比較沒奔跑空間，不過有跳跳馬及一些玩具稍微可玩，整體是個非常棒的營區哦！",
            "type": 2,
            "rating": 5,
            "publishedDate": "2018/12/13",
            "tokenization": "營主 | 熱情 | 活動 | 很棒 | 營區 | 營主 | 熱情 | 親切 | 夜間 | 煙火及 | 搗 | 麻 | 糬 | 動 | 好玩 | 整營區 | 歡笑聲 | 熱 | 水量 | 很大 | 很穩 | 可惜 | 兩 | 隻 | 超大 | 蜜蜂 | 飛來 | 飛去 | 搞 | 整家 | 人心惶惶 | 營主 | 熱心 | 幫忙 | 捕捉 | 害怕 | 滿帳 | 時 | 小孩 | 奔跑 | 空間 | 跳跳 | 馬 | 玩具 | 稍微 | 可玩 | 整體 | 棒 | 營區"
        },
        {
            "content": "設施很完善。營主很用心 營地規劃很好 活動也很多 兔子也很可愛",
            "type": 2,
            "rating": 5,
            "publishedDate": "2018/12/09",
            "tokenization": "設施 | 完善 | 營主 | 用心 | 營地 | 規劃 | 活動 | 兔子 | 愛"
        },
        {
            "content": "超熱情的營區^^。親子露營的好地方!",
            "type": 2,
            "rating": 5,
            "publishedDate": "2018/12/09",
            "tokenization": "超熱情 | 營區 | 親子 | 露營 | 地方"
        },
        {
            "content": "優良的親子露營區。建議加裝浴室吊掛衣服的裝置",
            "type": 2,
            "rating": 5,
            "publishedDate": "2018/12/03",
            "tokenization": "優良 | 親子 | 露營區 | 建議 | 加裝 | 浴室 | 吊掛 | 衣服 | 裝置"
        },
        {
            "content": "環境舒適，營主待人親切",
            "type": 2,
            "rating": 5,
            "publishedDate": "2018/11/28",
            "tokenization": "環境 | 舒適 | 營主 | 待人 | 親切"
        },
        {
            "content": "老闆很用心在經營營區。數不清的n露......營地很美，早上起床，空氣清新，心曠神怡離蓬萊溪護魚步道很近老闆很用心在經營營區活動準備得很豐富晚上，有打麻糬活動早上，做棉花糖大人小朋友都好開心",
            "type": 2,
            "rating": 5,
            "publishedDate": "2018/11/27",
            "tokenization": "老闆 | 用心 | 經營 | 營區 | 數不清 | n | 露 | 營地 | 美 | 早上 | 起床 | 空氣 | 清新 | 心曠 | 神怡離 | 蓬萊溪護 | 魚步 | 道 | 老闆 | 用心 | 經營 | 營區 | 活動 | 晚上 | 麻 | 糬 | 動 | 早上 | 做 | 棉花 | 糖 | 大人 | 小朋友 | 開心"
        },
        {
            "content": "營主很熱情，營區很棒，孩子的天堂。孩子們玩得超級高興的，高興的不想回家。下次一定還要在來營地露營。",
            "type": 2,
            "rating": 5,
            "publishedDate": "2018/11/26",
            "tokenization": "營主 | 很熱情 | 營區 | 很棒 | 孩子 | 天堂 | 孩子 | 玩 | 超級 | 不想 | 回家 | 下次 | 營地 | 露營"
        },
        {
            "content": "營地主人很用心，環境乾淨、還有很多設施，從早到晚活動很多！",
            "type": 2,
            "rating": 5,
            "publishedDate": "2018/11/26",
            "tokenization": "營地 | 主人 | 用心 | 環境 | 乾淨 | 設施 | 早 | 晚 | 活動"
        },
        {
            "content": "接待很親切熱情，活動也很適合孩子，很不錯的露營區",
            "type": 2,
            "rating": 5,
            "publishedDate": "2018/11/26",
            "tokenization": "接待 | 親切 | 熱情 | 活動 | 適合 | 孩子 | 很不錯 | 露營區"
        },
        {
            "content": "親切的營主,完善的設施",
            "type": 2,
            "rating": 5,
            "publishedDate": "2018/11/25",
            "tokenization": "親切 | 營主 | 完善 | 設施"
        },
        {
            "content": "很棒的營區，除了原有的設施外還帶DIY的活動，更豐富露營的樂趣！。如果小黑蚊能少些就更棒了。",
            "type": 2,
            "rating": 5,
            "publishedDate": "2018/11/25",
            "tokenization": "很棒 | 營區 | 原有 | 設施外 | 還帶 | DIY | 活動 | 露營 | 樂趣 | 小黑 | 蚊能 | 少些 | 棒"
        },
        {
            "content": "很用心的營區，營主都會辦一些小活動，如搗麻糬，讚",
            "type": 2,
            "rating": 4,
            "publishedDate": "2018/11/12",
            "tokenization": "用心 | 營區 | 營主 | 辦 | 小活動 | 搗 | 麻 | 糬 | 讚"
        },
        {
            "content": "舒適的大空間去不超收，小朋友可以去草皮跑，玩小河道漂漂河和彩色輪胎鞦韆，整體環境不錯，給營主按個讚。",
            "type": 2,
            "rating": 4,
            "publishedDate": "2018/11/07",
            "tokenization": "舒適 | 大空間 | 超收 | 小朋友 | 草皮 | 跑 | 玩小 | 河道 | 漂 | 漂河 | 彩色 | 輪胎 | 鞦 | 韆 | 整體 | 環境 | 不錯 | 營主 | 讚"
        },
        {
            "content": "營主很用心也很熱情，值得推薦好營地！",
            "type": 2,
            "rating": 5,
            "publishedDate": "2018/11/05",
            "tokenization": "營主 | 用心 | 熱情 | 值得 | 推薦 | 營地"
        },
        {
            "content": "很親切的營區，超級適合有小朋友的家庭一起露營，安全又好玩，也沒有太多坡度，讚!!",
            "type": 2,
            "rating": 5,
            "publishedDate": "2018/11/04",
            "tokenization": "親切 | 營區 | 超級 | 適合 | 小朋友 | 家庭 | 露營 | 好玩 | 太 | 坡度 | 讚"
        },
        {
            "content": "營區真的很棒，營帳不超收，有足夠空間，晚上有打麻吉活動，早上有做棉花糖活動，讓大小朋友都很開心。蚊子比較多，不過應該沒辦法，這就是露營要克服的",
            "type": 2,
            "rating": 5,
            "publishedDate": "2018/11/04",
            "tokenization": "營區 | 真的 | 很棒 | 營帳 | 超收 | 有足夠 | 空間 | 晚上 | 打麻吉 | 活動 | 早上 | 做 | 棉花 | 糖 | 活動 | 大小 | 朋友 | 開心 | 蚊子 | 辦法 | 露營 | 克服"
        },
        {
            "content": "畢竟是親子露營區希望抽煙味能少一點就更完美了。A區有狗大便希望能在注意點。",
            "type": 2,
            "rating": 5,
            "publishedDate": "2018/10/16",
            "tokenization": "畢 | 竟是 | 親子 | 露營區 | 希望 | 抽煙味 | 能少 | 一點 | 完美 | 區有 | 狗 | 大便 | 希望 | 點"
        },
        {
            "content": "親子露營的好地方，營主人親切、好客，廁所超乾淨，好多小孩遊樂設施，小朋友玩到都捨不得回家了。大推的營區，來了絕對不會後悔",
            "type": 2,
            "rating": 5,
            "publishedDate": "2018/10/09",
            "tokenization": "親子 | 露營 | 地方 | 營主 | 親切 | 好客 | 廁所 | 超乾淨 | 好多 | 小孩 | 遊樂 | 設施 | 小朋友 | 玩到 | 捨 | 回家 | 推 | 營區 | 不會後悔"
        },
        {
            "content": "很親切的營主！非常適合孩子的營區！好玩好好玩！",
            "type": 2,
            "rating": 5,
            "publishedDate": "2018/10/08",
            "tokenization": "親切 | 營主 | 適合 | 孩子 | 營區 | 好玩 | 好玩"
        },
        {
            "content": "會讓人覺得舒服放鬆的營區，值得再回訪",
            "type": 2,
            "rating": 5,
            "publishedDate": "2018/10/02",
            "tokenization": "人覺 | 舒服 | 放 | 鬆 | 營 | 區 | 值得 | 回訪"
        },
        {
            "content": "山景真的很漂亮，小朋友玩的很開心哦",
            "type": 2,
            "rating": 5,
            "publishedDate": "2018/09/30",
            "tokenization": "山景 | 真的 | 很漂亮 | 小朋友 | 玩 | 開心"
        },
        {
            "content": "令人滿意的好營地! 大推~。交通便利，縣道124轉進小路馬上就到。營主很親切，環境乾淨，草地舒適，親子設備多，小朋友玩的極開心，觀星也很適合。平日也推薦大家，很有包場的感覺唷。",
            "type": 2,
            "rating": 5,
            "publishedDate": "2018/09/29",
            "tokenization": "令人 | 滿意 | 營地 | 推 | 交通 | 便利 | 縣道 | 124 | 轉進 | 小路 | 馬 | 營主 | 親切 | 環境 | 乾淨 | 草地 | 舒適 | 親子 | 設備 | 小朋友 | 玩 | 極開心 | 觀星 | 適合 | 平日 | 推薦 | 包場 | 感覺 | 唷"
        },
        {
            "content": "不錯的營區，衛浴乾淨，營主有用心經營唷！",
            "type": 2,
            "rating": 5,
            "publishedDate": "2018/09/24",
            "tokenization": "不錯 | 營區 | 衛浴 | 乾淨 | 營主 | 用心 | 經營 | 唷"
        },
        {
            "content": "一畝田是個不錯的營區，衛浴乾淨。",
            "type": 2,
            "rating": 5,
            "publishedDate": "2018/09/24",
            "tokenization": "一畝 | 田 | 不錯 | 營區 | 衛浴 | 乾淨"
        },
        {
            "content": "棉花糖diy活動好好玩",
            "type": 2,
            "rating": 4,
            "publishedDate": "2018/09/24",
            "tokenization": "棉花 | 糖 | diy | 活動 | 好玩"
        },
        {
            "content": "規劃得很棒，謝謝營主的煙火秀和宵夜點心",
            "type": 2,
            "rating": 5,
            "publishedDate": "2018/09/23",
            "tokenization": "規劃 | 很棒 | 謝謝 | 營主 | 煙 | 火秀 | 宵夜 | 點心"
        },
        {
            "content": "適合較小小孩遊玩的環境。營主的接待態度需要更柔和一些，才不至於讓人有心情不美麗的狀況出現",
            "type": 2,
            "rating": 4,
            "publishedDate": "2018/09/19",
            "tokenization": "適合 | 小孩 | 遊玩 | 環境 | 營主 | 接待 | 態度 | 柔和 | 心情 | 不美麗 | 狀況"
        },
        {
            "content": "營區小孩設施很多，營主很用心，小孩玩的超開心，有給小孩體驗製作棉花糖跟搗麻吉活動真的好棒。營區蚊子多了一些（小黑蚊）如果少了它（小黑蚊），會更好。口袋名單",
            "type": 2,
            "rating": 5,
            "publishedDate": "2018/09/18",
            "tokenization": "營區 | 小孩 | 設施 | 營主 | 用心 | 小孩 | 玩 | 超開心 | 有給 | 小孩 | 體 | 驗 | 製 | 作 | 棉花 | 糖 | 搗 | 麻吉活動 | 真的 | 好棒 | 營區 | 蚊子 | 小黑 | 蚊 | 少 | 小黑 | 蚊 | 更好 | 口袋 | 名單"
        },
        {
            "content": "孩子們的遊戲天堂，大人們的悠哉天堂！",
            "type": 2,
            "rating": 5,
            "publishedDate": "2018/09/02",
            "tokenization": "孩子 | 遊戲 | 天堂 | 大人 | 悠哉 | 天堂"
        },
        {
            "content": "有機會會再來，孩子挺喜歡的。廁所有點味道，可能跟蹲式馬桶沖水的機制有關，如果只是輕踩無法全沖乾淨，要小踩一小段時間才能全沖掉，導致如廁時仍有上位使用者的尿液仍殘留在馬桶裡。",
            "type": 2,
            "rating": 5,
            "publishedDate": "2018/09/02",
            "tokenization": "機會會 | 孩子 | 挺 | 喜歡 | 廁 | 點 | 味道 | 蹲式 | 馬 | 桶 | 沖 | 水 | 機制 | 輕 | 踩 | 全 | 沖 | 乾淨 | 踩 | 一小 | 段 | 時間 | 全 | 沖 | 掉 | 導致 | 廁時 | 上位 | 使用者 | 尿液 | 仍殘 | 留在 | 馬 | 桶裡"
        },
        {
            "content": "營主熱情，設施很好，非常適合帶小孩來。",
            "type": 2,
            "rating": 5,
            "publishedDate": "2018/08/25",
            "tokenization": "營主 | 熱情 | 設施 | 適合帶 | 小孩"
        },
        {
            "content": "閑靜清幽的營地，設施完善適合親子同遊 營主親切 、熱心，還貼心的準備防蚊液，下次還會造訪",
            "type": 2,
            "rating": 5,
            "publishedDate": "2018/08/22",
            "tokenization": "閑 | 靜 | 清幽 | 營地 | 設施 | 完善 | 適合 | 親子 | 同遊 | 營主 | 親切 | 熱心 | 還貼 | 心 | 防蚊液 | 下次 | 還會 | 造訪"
        },
        {
            "content": "山嵐很美 秋千小孩玩瘋",
            "type": 2,
            "rating": 5,
            "publishedDate": "2018/08/22",
            "tokenization": "山嵐 | 美 | 秋千 | 小孩 | 玩 | 瘋"
        },
        {
            "content": "環境很好，生態很豐富，草皮的排水很好。營主安排搗麻吉的活動很適合親子同樂。",
            "type": 2,
            "rating": 5,
            "publishedDate": "2018/08/19",
            "tokenization": "環境 | 生態 | 草皮 | 排水 | 營主 | 安排 | 搗麻吉 | 活動 | 適合 | 親子 | 同樂"
        },
        {
            "content": "非常用心的營主。營地很多小地方都用心佈置，衛浴乾淨營主夫妻親切客氣，晚上還有搗麻糬體驗",
            "type": 2,
            "rating": 5,
            "publishedDate": "2018/08/18",
            "tokenization": "用心 | 營主 | 營地 | 地方 | 用心 | 佈 | 置 | 衛浴 | 乾淨 | 營主 | 夫妻 | 親切 | 客氣 | 晚上 | 搗 | 麻 | 糬 | 體 | 驗"
        },
        {
            "content": "營主親切，有煙火、跳跳馬、搗麻吉、喂兔子、玩水，玩不完，非常值回票價",
            "type": 2,
            "rating": 5,
            "publishedDate": "2018/08/17",
            "tokenization": "營主 | 親切 | 有煙火 | 跳跳 | 馬 | 搗麻吉 | 喂 | 兔子 | 玩水 | 玩 | 完 | 值 | 回票價"
        },
        {
            "content": "營主很用心，規劃的很好，下次還會再去",
            "type": 2,
            "rating": 5,
            "publishedDate": "2018/08/15",
            "tokenization": "營主 | 用心 | 規劃 | 下次 | 還會"
        },
        {
            "content": "適合小孩的優質營地！！！",
            "type": 2,
            "rating": 5,
            "publishedDate": "2018/08/12",
            "tokenization": "適合 | 小孩 | 優質 | 營地"
        },
        {
            "content": "值得一來。除了有小黑蚊之外，雖然是在夏天去但樹很多白天不至於過熱，晚上涼爽半夜的話吹電扇會冷，這次在a區離廁所有點遠稍有不便外整體感覺很不錯，比上次去四季非露不可感覺還棒，營位夠大營主用心給一個大大的讚。",
            "type": 2,
            "rating": 5,
            "publishedDate": "2018/08/12",
            "tokenization": "值得 | 小黑 | 蚊 | 之外 | 夏天 | 樹 | 白天 | 過熱 | 晚上 | 涼爽 | 半夜 | 話 | 吹 | 電扇 | 冷 | a | 區離 | 廁 | 點遠 | 稍 | 不便 | 外 | 整體 | 感覺 | 不錯 | 上次 | 四季 | 非露 | 感覺 | 還棒 | 營位夠 | 營主 | 用心 | 給一個 | 大大的 | 讚"
        },
        {
            "content": "環境不錯，帳篷旁邊居然看到啄木鳥，很特別的體驗。小孩玩盪鞦韆也玩瘋了",
            "type": 2,
            "rating": 5,
            "publishedDate": "2018/08/08",
            "tokenization": "環境 | 不錯 | 帳篷 | 旁邊 | 啄木 | 鳥 | 很特別 | 體驗 | 小孩 | 玩盪 | 鞦 | 韆 | 玩 | 瘋"
        },
        {
            "content": "閑靜清幽的營地，設施完善適合親子同遊。營主親切 、熱心，園區交通便捷，環境養護得很好。非常適合帶著全家一起同樂，也適合剛接觸露營的友善營區。",
            "type": 2,
            "rating": 5,
            "publishedDate": "2018/08/08",
            "tokenization": "閑 | 靜 | 清幽 | 營地 | 設施 | 完善 | 適合 | 親子 | 同遊 | 營主 | 親切 | 熱心 | 園區 | 交通 | 便捷 | 環境 | 養護 | 適合帶 | 著 | 全家 | 同樂 | 適合剛 | 接觸 | 露營 | 友善 | 營區"
        },
        {
            "content": "風景很棒!晚上還有搗麻糬活動 大人小孩同樂!",
            "type": 2,
            "rating": 5,
            "publishedDate": "2018/08/07",
            "tokenization": "風景 | 很棒 | 晚上 | 搗 | 麻 | 糬 | 動 | 大人 | 小孩 | 同樂"
        },
        {
            "content": "小朋友超喜歡，有小朋友戲水池，只是戲水池變變上漆的地方會滑要小心，營區老闆也很讚，下次有機會還會再來",
            "type": 2,
            "rating": 5,
            "publishedDate": "2018/08/06",
            "tokenization": "小朋友 | 超喜歡 | 小朋友 | 戲 | 水池 | 戲 | 水池 | 變變 | 漆 | 地方 | 會滑要 | 小心 | 營區 | 老闆 | 讚 | 下次 | 機會 | 還會"
        },
        {
            "content": "營主人太好客了，讓我們喂食兔兔、介紹可愛的咪咪，還送上親自做的拔絲地瓜，小孩吃的開心直說好吃～遊樂設。可惜有一點小黑蚊，不過也熱心提供防蚊液、蚊香，也有在處理小黑蚊不讓它繁殖！加油～",
            "type": 2,
            "rating": 5,
            "publishedDate": "2018/07/30",
            "tokenization": "營主 | 人太 | 好客 | 喂食 | 兔兔 | 介紹 | 可愛的 | 咪咪 | 還送 | 做 | 拔絲 | 地瓜 | 小孩 | 吃 | 開心 | 直 | 說 | 好吃 | 遊樂設 | 可惜 | 一點 | 小黑 | 蚊 | 熱心 | 提供 | 防蚊液 | 蚊香 | 小黑 | 蚊 | 繁殖 | 加油"
        },
        {
            "content": "營位很大給的粉大氣 …酥服",
            "type": 2,
            "rating": 5,
            "publishedDate": "2018/07/29",
            "tokenization": "營位 | 很大 | 給的 | 粉大氣 | 酥服"
        },
        {
            "content": "活動麻吉很好吃，是很溫馨很棒的營地，好棒!",
            "type": 2,
            "rating": 5,
            "publishedDate": "2018/07/29",
            "tokenization": "活動 | 麻吉 | 好吃 | 溫馨 | 很棒 | 營地 | 好棒"
        },
        {
            "content": "超舒服，超休閒的營區，讚啦",
            "type": 2,
            "rating": 5,
            "publishedDate": "2018/07/29",
            "tokenization": "超 | 舒服 | 超休 | 閒 | 營區 | 讚"
        },
        {
            "content": "營主很親切。如果有飲水機更好",
            "type": 2,
            "rating": 3,
            "publishedDate": "2018/07/29",
            "tokenization": "營主 | 親切 | 飲水機 | 更好"
        },
        {
            "content": "貼心營主。我還會在來的。",
            "type": 2,
            "rating": 5,
            "publishedDate": "2018/07/28",
            "tokenization": "貼心 | 營主 | 還會"
        },
        {
            "content": "環境整潔，而且風景超美的啦！",
            "type": 2,
            "rating": 5,
            "publishedDate": "2018/07/27",
            "tokenization": "環境 | 整潔 | 風景超 | 美的"
        },
        {
            "content": "環境真的很好，拔絲地瓜好吃到念念不忘。營主人真的很好，服務好到沒話說，唯一遇到一個問題就是水溫不穩⋯只能把水放到水桶裏調好溫度在幫小朋友洗澡，除此之外只有*讚*可以形容。",
            "type": 2,
            "rating": 5,
            "publishedDate": "2018/07/25",
            "tokenization": "環境 | 真的 | 拔絲 | 地瓜 | 好吃 | 念念不忘 | 營主 | 真的 | 服務好 | 沒話 | 說 | 唯一 | 水溫 | 不穩 | 只能 | 水 | 放到 | 水桶 | 裏 | 調好 | 溫度 | 幫 | 小朋友 | 洗澡 | 讚 | 形容"
        },
        {
            "content": "值得再來，親子露營大推！",
            "type": 2,
            "rating": 4,
            "publishedDate": "2018/07/23",
            "tokenization": "值得 | 再來 | 親子 | 露營 | 推"
        },
        {
            "content": "想再去的地方。雖然天氣炎熱，但寬闊的場地讓人覺得寬敞的舒服，沒有帳帳相連；親子戲水設施，徹底的給大人放空的機會，是讓我會想再度造訪及多露幾天的好地方。",
            "type": 2,
            "rating": 5,
            "publishedDate": "2018/07/21",
            "tokenization": "想 | 地方 | 天氣 | 炎熱 | 寬闊 | 場地 | 人覺 | 寬 | 敞 | 舒服 | 帳帳 | 相連 | 親子 | 戲水 | 設施 | 的給 | 大人 | 放空 | 機會 | 想 | 再度 | 造訪 | 多露 | 幾天 | 地方"
        },
        {
            "content": "很棒的營地，可惜小黑蚊很多，小朋友兩隻腳都是紅豆冰了",
            "type": 2,
            "rating": 5,
            "publishedDate": "2018/07/17",
            "tokenization": "很棒 | 營地 | 可惜 | 小黑 | 蚊 | 小朋友 | 兩 | 隻 | 腳 | 紅豆冰"
        },
        {
            "content": "營位很大，營主很用心經營",
            "type": 2,
            "rating": 5,
            "publishedDate": "2018/07/17",
            "tokenization": "營位 | 很大 | 營主 | 用心 | 經營"
        },
        {
            "content": "環境設施設備都很優質。營地離蓬萊護魚步道不遠,離老街近,馬路邊還有雜貨店可以補給,營地草地算不錯~ 玩水,沙坑,盪鞦韆,冰箱,一應俱全,晚上還有打麻薯活動~營主輕切,小妹整理環境也太努力, 改天必定回訪！!!",
            "type": 2,
            "rating": 5,
            "publishedDate": "2018/07/17",
            "tokenization": "環境 | 設施 | 設備 | 優質 | 營地離 | 蓬萊護 | 魚步 | 道 | 不遠 | 老街 | 馬 | 路邊 | 雜貨店 | 補給 | 營地 | 草地 | 算不錯 | 玩水 | 沙坑 | 盪 | 鞦 | 韆 | 冰箱 | 一應 | 俱全 | 晚上 | 麻薯 | 活動 | 營主 | 輕切 | 小妹 | 整理 | 環境 | 太 | 努力 | 改天 | 回訪"
        },
        {
            "content": "景色佳，設施優，營主熱情，廁所大又乾淨，地板架高穿脫衣服不沾濕，還提供防蚊液，下雨排水快，推",
            "type": 2,
            "rating": 5,
            "publishedDate": "2018/07/15",
            "tokenization": "景色 | 佳 | 設施 | 優 | 營主 | 熱情 | 廁所大 | 乾淨 | 地板 | 架 | 高 | 穿 | 脫 | 衣服 | 不沾濕 | 提供 | 防蚊液 | 下雨 | 排水 | 推"
        },
        {
            "content": "營主人很好，環境很乾淨。可以多一些路標，比較好找",
            "type": 2,
            "rating": 5,
            "publishedDate": "2018/07/14",
            "tokenization": "營主 | 環境 | 乾淨 | 多一些 | 路標 | 好找"
        },
        {
            "content": "老闆很用心，值得一住的好地方",
            "type": 2,
            "rating": 5,
            "publishedDate": "2018/07/09",
            "tokenization": "老闆 | 用心 | 值得 | 一住 | 地方"
        },
        {
            "content": "用心經營的營區，夜間活動讓大人小孩都能參與、兒童戲水玩的開心。較可惜是我們遇上大量蒼蠅攻擊，詢問老板之後才了解是整個南庄生態被破壞了。希望我們遇到情況能被改善了。",
            "type": 2,
            "rating": 5,
            "publishedDate": "2018/07/09",
            "tokenization": "用心 | 經營 | 營區 | 夜間 | 活動 | 大人 | 小孩 | 參 | 兒童 | 戲水 | 玩 | 開心 | 可惜 | 遇上 | 蒼蠅 | 攻擊 | 詢問 | 老板 | 之後才 | 南庄 | 生態 | 破壞 | 希望 | 情況 | 改善"
        },
        {
            "content": "營主服務很好。草皮區景色好。環境乾淨。。。Ａ區可以加設搖椅及盪鞦韆會更完美。",
            "type": 2,
            "rating": 5,
            "publishedDate": "2018/07/08",
            "tokenization": "營主 | 服務 | 草皮 | 區 | 景色 | 環境 | 乾淨 | 區 | 加設 | 搖椅 | 及盪 | 鞦 | 韆 | 完美"
        },
        {
            "content": "很棒的營區，下次會再來唷！",
            "type": 2,
            "rating": 5,
            "publishedDate": "2018/07/07",
            "tokenization": "很棒 | 營區 | 下次 | 唷"
        },
        {
            "content": "非常好的營區，還會再去",
            "type": 2,
            "rating": 5,
            "publishedDate": "2018/07/04",
            "tokenization": "營區 | 還會"
        },
        {
            "content": "美麗的營區 處處可見營主的用心",
            "type": 2,
            "rating": 5,
            "publishedDate": "2018/07/01",
            "tokenization": "美麗 | 營區 | 營主 | 用心"
        },
        {
            "content": "讓小孩放電的好地方。我們的第二露獻給了一畝田也是單飛第一露！帶著雙寶！小孩在飄飄河玩得不亦樂乎！雖然晚上下了場大雨但不影響排水系統也不錯",
            "type": 2,
            "rating": 5,
            "publishedDate": "2018/07/01",
            "tokenization": "小孩 | 放電 | 地方 | 露獻給 | 一畝 | 田 | 單飛 | 第一 | 露 | 帶著 | 雙寶 | 小孩 | 飄飄河 | 玩 | 晚上 | 下了場 | 大雨 | 影響 | 排水 | 系統 | 不錯"
        },
        {
            "content": "謝謝你們的貼心服務，幫我們解決問題，還請我們吃小點心",
            "type": 2,
            "rating": 5,
            "publishedDate": "2018/06/25",
            "tokenization": "謝謝 | 貼 | 心服 | 務 | 幫 | 解決 | 還請 | 吃 | 小點心"
        },
        {
            "content": "有水池 沙坑 鞦韆 早上兔子餵養 晚上搗麻糬 很棒的營區 很用心的營主",
            "type": 2,
            "rating": 5,
            "publishedDate": "2018/06/25",
            "tokenization": "水池 | 沙坑 | 鞦 | 韆 | 早上 | 兔子 | 餵養 | 晚上 | 搗 | 麻 | 糬 | 很棒 | 營區 | 用心 | 營主"
        },
        {
            "content": "一畝田的環境很棒喔，有漂漂河，小泳池，沙坑，以及盪鞦韆，非常適合小朋友。營主用心準備的搗麻糬還有煙火。浴室的熱水不穩，不是太熱，就是太冷，無法定在正確的溫度，熱水的溫度建議做改善，洗澡才不會一直再調溫度。",
            "type": 2,
            "rating": 5,
            "publishedDate": "2018/06/24",
            "tokenization": "一畝 | 田 | 環境 | 很棒 | 喔 | 漂 | 漂河 | 泳池 | 沙坑 | 盪 | 鞦 | 韆 | 適合 | 小朋友 | 營主 | 用心 | 搗 | 麻 | 糬 | 煙 | 火 | 浴室 | 熱水 | 不穩 | 太熱 | 太冷 | 法定 | 正確 | 溫度 | 熱水 | 溫度 | 建議 | 做 | 改善 | 洗澡 | 再調 | 溫度"
        },
        {
            "content": "排水做的很好，當天午後超大雷雨都沒淹水。小孩玩樂設施很多，小水池設計相當好安全又乾淨，大人可以放鬆露。謝謝營主用心經營營區，小孩玩得很開心，值得在訪好露營區！",
            "type": 2,
            "rating": 5,
            "publishedDate": "2018/06/24",
            "tokenization": "排水 | 做 | 當天午 | 超大 | 雷雨 | 淹水 | 小孩 | 玩樂 | 設施 | 水池 | 設計 | 乾淨 | 大人 | 放 | 鬆 | 露 | 謝謝 | 營主 | 用心 | 經營 | 營區 | 小孩 | 玩得 | 開心 | 值得 | 訪好 | 露營區"
        },
        {
            "content": "很適合小朋友的露營區，交通方便，推薦",
            "type": 2,
            "rating": 5,
            "publishedDate": "2018/06/24",
            "tokenization": "適合 | 小朋友 | 露營區 | 交通 | 推薦"
        },
        {
            "content": "熱門的營區，幸運能訂到！不過南庄露營目前還是下雨全壘打…",
            "type": 2,
            "rating": 4,
            "publishedDate": "2018/06/23",
            "tokenization": "熱門 | 營區 | 幸運能 | 訂到 | 南庄 | 露營 | 下雨 | 全壘"
        },
        {
            "content": "營主人超讚 營地也都很優 這次遇到下雨 會在找一次好天氣在來",
            "type": 2,
            "rating": 5,
            "publishedDate": "2018/06/20",
            "tokenization": "營主 | 超 | 讚 | 營地 | 優 | 下雨 | 找 | 天氣"
        },
        {
            "content": "環境很讚，衛浴很乾淨。游泳池能在整理一下，不要有寶特瓶在水裡，這樣就更讚",
            "type": 2,
            "rating": 5,
            "publishedDate": "2018/06/19",
            "tokenization": "環境 | 讚 | 衛浴 | 乾淨 | 游泳池 | 整理 | 有寶特瓶 | 水裡 | 讚"
        },
        {
            "content": "值得推薦的營區。適合親子同樂的好營區",
            "type": 2,
            "rating": 5,
            "publishedDate": "2018/06/17",
            "tokenization": "值得 | 推薦 | 營區 | 適合 | 親子 | 同樂 | 營區"
        },
        {
            "content": "首露能有這麼好的營區真的很開心~值得回露!。親子設施不錯，草皮厚實，衛浴乾淨，大大的冰箱，還有親切的營主唯一美中不足的是當天的露友帶了狗狗，便便沒處理，差點踩到",
            "type": 2,
            "rating": 5,
            "publishedDate": "2018/06/12",
            "tokenization": "首露 | 營區 | 真的 | 開心 | 值得 | 回露 | 親子 | 設施 | 不錯 | 草皮 | 厚實 | 衛浴 | 乾淨 | 大大的 | 冰箱 | 親切 | 營主 | 唯一 | 美中不足 | 當天 | 露友 | 狗狗 | 差點 | 踩"
        },
        {
            "content": "營區很乾淨漂亮，適合有小朋友的家庭來玩",
            "type": 2,
            "rating": 5,
            "publishedDate": "2018/06/11",
            "tokenization": "營區 | 乾淨 | 漂亮 | 適合 | 小朋友 | 家庭 | 玩"
        },
        {
            "content": "營主人親切且和善，甚至還有搗麻糬的活動，整體環境規劃完善",
            "type": 2,
            "rating": 4,
            "publishedDate": "2018/06/06",
            "tokenization": "營主 | 人親 | 切且 | 和善 | 搗 | 麻 | 糬 | 動 | 整體 | 環境 | 規劃 | 完善"
        },
        {
            "content": "續露一晚 服務品質依舊",
            "type": 2,
            "rating": 5,
            "publishedDate": "2018/06/04",
            "tokenization": "續露 | 一晚 | 服務品 | 質依舊"
        },
        {
            "content": "可以讓小孩脫離3C不無聊的好營地",
            "type": 2,
            "rating": 5,
            "publishedDate": "2018/06/04",
            "tokenization": "小孩 | 脫離 | 3C | 不無聊 | 營地"
        },
        {
            "content": "是一個地方優美及適合小朋友遊戲的營地，值得下次在去。熱水器忽冷忽熱唯一美中不足",
            "type": 2,
            "rating": 5,
            "publishedDate": "2018/06/03",
            "tokenization": "地方 | 優美及 | 適合 | 小朋友 | 遊戲 | 營地 | 值得 | 下次 | 熱 | 水器 | 忽冷 | 忽熱 | 唯一 | 美中不足"
        },
        {
            "content": "營主很親切，草地很棒！",
            "type": 2,
            "rating": 5,
            "publishedDate": "2018/06/03",
            "tokenization": "營主 | 親切 | 草地 | 很棒"
        },
        {
            "content": "營主用心建設各項設施還安排活動 人超好相處。請在a區增設兒童遊樂設施",
            "type": 2,
            "rating": 5,
            "publishedDate": "2018/06/03",
            "tokenization": "營主 | 用心 | 建設 | 各項 | 設施還 | 安排 | 活動 | 人超 | 相處 | 請 | a | 區增 | 設兒 | 童遊樂 | 設施"
        },
        {
            "content": "露營新手首露，非常棒的營地，大人小孩都玩得很開心。路口可以再放一些指示牌，比較不會錯過",
            "type": 2,
            "rating": 5,
            "publishedDate": "2018/05/27",
            "tokenization": "露營 | 新手 | 首露 | 棒 | 營地 | 大人 | 小孩 | 玩 | 開心 | 路口 | 再放 | 指示牌 | 錯過"
        },
        {
            "content": "洗手台附有洗手乳及防蚊液，晚上還有放煙火及搗麻糬活動，看得出營主的用心。。我們住在A區，樹蔭下搭帳，相當涼爽，環境清幽。建議A區可新增一道階梯通到B區衛浴，這樣更便利。",
            "type": 2,
            "rating": 5,
            "publishedDate": "2018/05/26",
            "tokenization": "洗手台 | 附有 | 洗手 | 乳及 | 防蚊液 | 晚上 | 放煙 | 火及 | 搗 | 麻 | 糬 | 動 | 看得出 | 營主 | 用心 | 住 | 區 | 樹蔭下 | 搭帳 | 涼爽 | 環境 | 清幽 | 建議 | 區可 | 新增 | 一道 | 階梯 | 通到 | B | 區衛浴 | 便利"
        },
        {
            "content": "寬闊，完善，乾淨的場地",
            "type": 2,
            "rating": 5,
            "publishedDate": "2018/05/26",
            "tokenization": "寬闊 | 完善 | 乾淨 | 場地"
        },
        {
            "content": "環境品質很好，營主很親切，",
            "type": 2,
            "rating": 5,
            "publishedDate": "2018/05/26",
            "tokenization": "環境 | 品質 | 營主 | 親切"
        },
        {
            "content": "草皮很優，很用心整理。美中不足的地方，熱水太燙，接洗澡水的桶子，真的太小，其餘的真的無可挑剔。。",
            "type": 2,
            "rating": 5,
            "publishedDate": "2018/05/20",
            "tokenization": "草皮 | 很優 | 用心 | 整理 | 美中不足 | 地方 | 熱水 | 太 | 燙 | 接 | 洗澡水 | 桶子 | 真的 | 太小 | 真的 | 無可 | 挑剔"
        },
        {
            "content": "營主超NICE，很推薦的營地，下次一定會再來",
            "type": 2,
            "rating": 5,
            "publishedDate": "2018/05/19",
            "tokenization": "營主 | 超 | NICE | 推薦 | 營地 | 下次"
        },
        {
            "content": "環境優美，緊鄰蓬萊溪護魚步道",
            "type": 2,
            "rating": 5,
            "publishedDate": "2018/05/14",
            "tokenization": "環境 | 優美 | 緊鄰 | 蓬萊溪護 | 魚步 | 道"
        },
        {
            "content": "風景不錯，煙火搗麻糬好玩",
            "type": 2,
            "rating": 5,
            "publishedDate": "2018/05/14",
            "tokenization": "風景 | 不錯 | 煙火 | 搗 | 麻 | 糬 | 好玩"
        },
        {
            "content": "很用心的營主，非常棒的營地，小孩玩得超盡興",
            "type": 2,
            "rating": 5,
            "publishedDate": "2018/05/13",
            "tokenization": "用心 | 營主 | 棒 | 營地 | 小孩 | 玩得 | 超盡興"
        },
        {
            "content": "環境整潔，服務熱忱，用心經營",
            "type": 2,
            "rating": 5,
            "publishedDate": "2018/05/12",
            "tokenization": "環境 | 整潔 | 服務 | 熱忱 | 用心 | 經營"
        },
        {
            "content": "很棒的露營取，環境很好，設施也很多，讓小朋友玩的很開心",
            "type": 2,
            "rating": 5,
            "publishedDate": "2018/05/12",
            "tokenization": "很棒 | 露營取 | 環境 | 設施 | 小朋友 | 玩 | 開心"
        },
        {
            "content": "營主超用心，環境很好，有機會下次還要造訪",
            "type": 2,
            "rating": 5,
            "publishedDate": "2018/05/12",
            "tokenization": "營主 | 超 | 用心 | 環境 | 機會 | 下次 | 造訪"
        },
        {
            "content": "一畝田親子露營區～營主很用心對待每位露友就像回到家的感覺",
            "type": 2,
            "rating": 5,
            "publishedDate": "2018/05/08",
            "tokenization": "一畝 | 田 | 親子 | 露營區 | 營主 | 用心 | 每位 | 露友 | 回到 | 家 | 感覺"
        },
        {
            "content": "超讚！。我們一家首露獻給一畝田 謝謝營主給我們一家留個美好的回憶 環境 衛生 好的沒話說！營主又熱情 如果早給分數 我會給101分！讚讚讚～",
            "type": 2,
            "rating": 5,
            "publishedDate": "2018/05/05",
            "tokenization": "超 | 讚 | 一家 | 首露獻給 | 一畝 | 田 | 謝謝 | 營主 | 給我們 | 一家 | 留個 | 美好 | 回憶 | 環境 | 衛生 | 沒話 | 說 | 營主 | 熱情 | 早給 | 分數 | 我會給 | 101 | 分 | 讚 | 讚 | 讚"
        },
        {
            "content": "真的很適合親子露營的好地方",
            "type": 2,
            "rating": 5,
            "publishedDate": "2018/05/05",
            "tokenization": "真的 | 適合 | 親子 | 露營 | 地方"
        },
        {
            "content": "營主熱情，小黑紋也很熱情。",
            "type": 2,
            "rating": 5,
            "publishedDate": "2018/05/02",
            "tokenization": "營主 | 熱情 | 小黑 | 紋 | 熱情"
        },
        {
            "content": "很適合親子同樂的營區，營主用心的安排搗麻糬、看螢火蟲活動！ 推薦造訪看看唷",
            "type": 2,
            "rating": 5,
            "publishedDate": "2018/04/23",
            "tokenization": "適合 | 親子 | 同樂 | 營區 | 營主 | 用心 | 安排 | 搗 | 麻 | 糬 | 螢火蟲 | 活動 | 推薦 | 造訪 | 唷"
        },
        {
            "content": "繼續保持!!。晚上10點之後還是有很多人在吵鬧..這點希望可以管理改善..除此之外絕對是必來的露營區啦!",
            "type": 2,
            "rating": 5,
            "publishedDate": "2018/04/10",
            "tokenization": "晚上 | 10 | 點之後還 | 吵 | 鬧 | 希望 | 管理 | 改善 | 必來 | 露營區"
        },
        {
            "content": "繼續保持！絕對要再去。評價高果然是有原因的，大草皮保養得好而且小孩玩的空間和設施都不錯～滿帳也不覺得擁擠。浴室廁所數量都很夠，如果硬要挑毛病就是廁所可以再更經常性的巡視清潔一下。整體都滿意到爆棚！不過山路很暈記得吃暈車藥",
            "type": 2,
            "rating": 5,
            "publishedDate": "2018/04/10",
            "tokenization": "評價 | 高 | 原因 | 草皮 | 保養 | 小孩 | 玩 | 空間 | 設施 | 不錯 | 滿帳 | 不覺 | 擁擠 | 浴室 | 廁所 | 數量 | 很夠 | 硬要 | 挑毛病 | 廁所 | 更經 | 常性 | 巡視 | 清潔 | 整體 | 滿意 | 爆棚 | 山路 | 很暈 | 記得 | 吃 | 暈車藥"
        },
        {
            "content": "營區設施完善，乾淨，營主很nice，讚！",
            "type": 2,
            "rating": 5,
            "publishedDate": "2018/04/09",
            "tokenization": "營區 | 設施 | 完善 | 乾淨 | 營主 | nice | 讚"
        },
        {
            "content": "營主很用心很有人情味，小孩玩得很安全。",
            "type": 2,
            "rating": 5,
            "publishedDate": "2018/04/08",
            "tokenization": "營主 | 用心 | 人情味 | 小孩 | 玩得"
        },
        {
            "content": "住宿在A區碎石區，眼前滿滿山景真棒！。如果碎石區也有棧板可以用，那就更十全十美了。",
            "type": 2,
            "rating": 5,
            "publishedDate": "2018/04/08",
            "tokenization": "住宿 | 區 | 碎石 | 區 | 眼前 | 滿滿 | 山景 | 真棒 | 碎石 | 區也 | 棧板 | 十全十美"
        },
        {
            "content": "貼心、無什麼缺點的營區。晚上有搗麻薯活動，另一晚還有拔絲地瓜可吃，小孩好開心……感謝貼心的老闆洗手台很近、廁所也會定時清理、覺得整個設計都是有花心思的，值得推薦的營區",
            "type": 2,
            "rating": 5,
            "publishedDate": "2018/04/08",
            "tokenization": "貼心 | 無什麼 | 缺點 | 營區 | 晚上 | 搗 | 麻薯 | 活動 | 一晚 | 拔絲 | 地瓜 | 吃 | 小孩 | 開心 | 感謝 | 貼心 | 老闆 | 洗手台 | 很近 | 廁所 | 會定 | 時 | 清理 | 設計 | 花心思 | 值得 | 推薦 | 營區"
        },
        {
            "content": "營主有心經營，衛浴乾淨又香，讓我們會想再來!。建議搗麻糬活動，可以多組進行，要不人真的太多了/或者可以音樂帶動唱/烤蛇餅/DIY活動……等等，很期待喔!",
            "type": 2,
            "rating": 4,
            "publishedDate": "2018/04/07",
            "tokenization": "營主 | 有心 | 經營 | 衛浴 | 乾淨 | 香 | 想 | 建議 | 搗 | 麻 | 糬 | 動 | 多組 | 不人 | 真的 | 太多 | 音樂 | 帶動 | 唱 | 烤蛇餅 | DIY | 活動 | 期待 | 喔"
        },
        {
            "content": "老闆態度很好，環境好小孩玩得很開心喔！",
            "type": 2,
            "rating": 5,
            "publishedDate": "2018/04/06",
            "tokenization": "老闆 | 態度 | 環境 | 小孩 | 玩得 | 開心 | 喔"
        },
        {
            "content": "優質營區 乾淨整潔 兒童遊戲區數個 定時清潔 熱心協助 我們還會再來喔",
            "type": 2,
            "rating": 5,
            "publishedDate": "2018/04/05",
            "tokenization": "優質 | 營區 | 乾淨 | 整潔 | 兒童 | 遊戲區 | 數個 | 定時 | 清潔 | 熱心 | 協助 | 還會 | 喔"
        },
        {
            "content": "景觀設施都不錯的營區，鄰近南庄老街，可以順道旅遊吃美食。",
            "type": 2,
            "rating": 4,
            "publishedDate": "2018/04/05",
            "tokenization": "景觀 | 設施 | 不錯 | 營區 | 鄰近 | 南庄 | 老街 | 順道 | 旅遊 | 吃 | 美食"
        },
        {
            "content": "對我而言Cp 值很高的營地。真的放鬆的營地",
            "type": 2,
            "rating": 5,
            "publishedDate": "2018/04/04",
            "tokenization": "Cp | 值 | 高 | 營地 | 真的 | 放 | 鬆 | 營"
        },
        {
            "content": "細心，親子設備完善。鄰近護漁步道，步行幾分鐘，另南庄老街車程10分鐘，晚上有客家搗麻糬活動，有兔子可以餵養，還有送枝仔冰，夏天有戲水道，沙坑有遮陽，盪鞦韆有封住輪胎中間很細心",
            "type": 2,
            "rating": 5,
            "publishedDate": "2018/03/25",
            "tokenization": "細心 | 親子 | 設備 | 完善 | 鄰近護 | 漁步 | 道 | 步行 | 幾分鐘 | 南庄 | 老街 | 車程 | 10 | 分鐘 | 晚上 | 客家 | 搗 | 麻 | 糬 | 動 | 兔子 | 餵養 | 送枝 | 仔冰 | 夏天 | 有戲 | 水道 | 沙坑 | 遮陽 | 盪 | 鞦 | 韆 | 封 | 住 | 輪 | 胎 | 中 | 間 | 細 | 心"
        },
        {
            "content": "老闆很細心，設想周到。有客家搗麻糬，有兔子可以餵養，還有送枝仔冰，夏天有戲水道",
            "type": 2,
            "rating": 5,
            "publishedDate": "2018/03/25",
            "tokenization": "老闆 | 很細心 | 設想 | 周到 | 客家 | 搗 | 麻 | 糬 | 兔子 | 餵養 | 送枝 | 仔冰 | 夏天 | 有戲 | 水道"
        },
        {
            "content": "營主很用心，營地位置夠大，草皮很舒服，孩子們玩的很開心！",
            "type": 2,
            "rating": 5,
            "publishedDate": "2018/03/25",
            "tokenization": "營主 | 用心 | 營地 | 位置 | 夠大 | 草皮 | 舒服 | 孩子 | 玩 | 開心"
        },
        {
            "content": "謝謝營主用心經營，大人小孩都有個難忘的回憶",
            "type": 2,
            "rating": 5,
            "publishedDate": "2018/03/25",
            "tokenization": "謝謝 | 營主 | 用心 | 經營 | 大人 | 小孩 | 難 | 忘 | 回憶"
        },
        {
            "content": "很平整的營地，營主很貼心，碎石地有提供塑膠格地墊而且搭營還留有空間讓孩子奔跑，設施也讓孩子們玩得開心",
            "type": 2,
            "rating": 5,
            "publishedDate": "2018/03/18",
            "tokenization": "平整 | 營地 | 營主 | 貼心 | 碎石 | 地有 | 提供 | 塑膠格 | 墊 | 搭營還 | 留有 | 空間 | 孩子 | 奔跑 | 設施 | 孩子 | 玩 | 開心"
        },
        {
            "content": "營主很親切，營地很舒服，臨近護魚步道很棒的營區",
            "type": 2,
            "rating": 5,
            "publishedDate": "2018/03/17",
            "tokenization": "營主 | 親切 | 營地 | 舒服 | 臨近護 | 魚步 | 道 | 很棒 | 營區"
        },
        {
            "content": "環境非常的適合孩子玩樂父母發呆聊天，",
            "type": 2,
            "rating": 5,
            "publishedDate": "2018/03/17",
            "tokenization": "環境 | 適合 | 孩子 | 玩樂 | 父母 | 發呆 | 聊天"
        },
        {
            "content": "風景宜人、乾淨的露營好所在。。1.建議流理台高度再調高一點，不然彎腰處理食材真的會造成腰背的壓力。2.廁所若可以定時清潔必然更棒3.晚上盥洗時熱水不穩定",
            "type": 2,
            "rating": 4,
            "publishedDate": "2018/03/11",
            "tokenization": "風景 | 宜人 | 乾淨 | 露營 | 建議 | 流理台 | 高度 | 再調 | 高一 | 點 | 彎腰 | 食材 | 真的 | 腰背 | 壓力 | 廁所若 | 定時 | 清潔 | 更棒 | 晚上 | 盥洗 | 時熱水 | 穩定"
        },
        {
            "content": "很好。不錯的營區!搗麻糬很有趣!",
            "type": 2,
            "rating": 5,
            "publishedDate": "2018/03/11",
            "tokenization": "不錯 | 營區 | 搗 | 麻 | 糬 | 有趣"
        },
        {
            "content": "營主很用心經營，很多小朋友玩的遊樂設施都弄的很好!營位也很大，相信以後植栽長大了，景會更漂亮~。真的是很適合小孩的親子營地，大推~",
            "type": 2,
            "rating": 5,
            "publishedDate": "2018/03/06",
            "tokenization": "營主 | 用心 | 經營 | 小朋友 | 玩 | 遊樂 | 設施 | 弄 | 營位 | 很大 | 以後植 | 栽長 | 景會 | 漂亮 | 真的 | 適合 | 小孩 | 親子 | 營地 | 推"
        },
        {
            "content": "假日還安排搗麻糬活動，很棒。",
            "type": 2,
            "rating": 5,
            "publishedDate": "2018/03/04",
            "tokenization": "假日 | 安排 | 搗 | 麻 | 糬 | 動 | 很棒"
        },
        {
            "content": "營主很用心的經營，還放煙火及搗麻糬，小孩玩的很開心",
            "type": 2,
            "rating": 4,
            "publishedDate": "2018/03/04",
            "tokenization": "營主 | 用心 | 經營 | 還放煙 | 火及 | 搗 | 麻 | 糬 | 小孩 | 玩 | 開心"
        },
        {
            "content": "不錯的親子營區，小孩玩的很開心。浴室不夠，洗澡要排隊",
            "type": 2,
            "rating": 5,
            "publishedDate": "2018/03/04",
            "tokenization": "不錯 | 親子 | 營區 | 小孩 | 玩 | 開心 | 浴室 | 洗澡 | 排隊"
        },
        {
            "content": "設備很新，環境乾淨，風景優，老闆親切。希望可以一直維持下去",
            "type": 2,
            "rating": 5,
            "publishedDate": "2018/02/27",
            "tokenization": "設備 | 新 | 環境 | 乾淨 | 風景優 | 老闆 | 親切 | 希望"
        },
        {
            "content": "好山好水 好舒服的營地",
            "type": 2,
            "rating": 5,
            "publishedDate": "2018/02/24",
            "tokenization": "好山好水 | 舒服 | 營地"
        },
        {
            "content": "景觀怡人、草皮漂亮、親子設施豐富（有鞦韆、沙坑、戲水池、還有養小兔子），營主夫妻非常親切，很用心經營",
            "type": 2,
            "rating": 5,
            "publishedDate": "2018/02/18",
            "tokenization": "景觀怡 | 草皮 | 漂亮 | 親子 | 設施 | 鞦 | 韆 | 沙坑 | 戲 | 水池 | 還有養 | 小兔子 | 營主 | 夫妻 | 親切 | 用心 | 經營"
        },
        {
            "content": "不錯的營地。熱水穩定、山景環繞清幽，營區環境很乾淨，活動空間大，營主有用心經營，希望洗滌區可以有遮陽傘，也機會會再去",
            "type": 2,
            "rating": 5,
            "publishedDate": "2018/02/13",
            "tokenization": "不錯 | 營地 | 熱水 | 穩定 | 山景 | 環繞 | 清幽 | 營區 | 環境 | 乾淨 | 活動 | 空間 | 營主 | 用心 | 經營 | 希望 | 洗滌區 | 遮陽傘 | 機會會"
        },
        {
            "content": "設施完善，乾淨整潔，服務熱忱",
            "type": 2,
            "rating": 5,
            "publishedDate": "2018/02/10",
            "tokenization": "設施 | 完善 | 乾淨 | 整潔 | 服務 | 熱忱"
        },
        {
            "content": "環境很棒，營位很大，值得再去的好營區",
            "type": 2,
            "rating": 5,
            "publishedDate": "2018/01/30",
            "tokenization": "環境 | 很棒 | 營位 | 很大 | 值得 | 營區"
        },
        {
            "content": "用心的營主，時時關心露客需求，場地大，不超收，值得一去！",
            "type": 2,
            "rating": 5,
            "publishedDate": "2018/01/30",
            "tokenization": "用心 | 營主 | 時時 | 關心 | 露客 | 需求 | 場地 | 超收 | 值得 | 一去"
        },
        {
            "content": "大推薦給喜歡露營的營友。去營地的時候營主介紹營區，和有需要什麼物品跟營主借，營主都說好，而且人超親切，晚上還有搗麻吉活動大人小孩都玩的不意樂乎，夏天還有泳池 是個會在想去的營地。",
            "type": 2,
            "rating": 5,
            "publishedDate": "2018/01/28",
            "tokenization": "推薦 | 給喜歡 | 露營 | 營友 | 營地 | 營主 | 介紹 | 營區 | 物品 | 營主 | 營主 | 說 | 人超 | 親切 | 晚上 | 搗 | 麻吉活動 | 大人 | 小孩 | 玩 | 不意 | 樂乎 | 夏天 | 泳池 | 想 | 營地"
        },
        {
            "content": "營主人超好，2017/10才開幕，營地超新衛浴也很乾淨，有求必應的營主第一次遇到  必推營地，海拔5。營主人超好，2017/10才開幕，營地超新衛浴也很乾淨，有求必應的營主第一次遇到  必推營地，海拔500左右， 還有沙坑和秋韆適合小朋友",
            "type": 2,
            "rating": 5,
            "publishedDate": "2018/01/28",
            "tokenization": "營主 | 人超 | 2017 | 10 | 開幕 | 營地 | 超新衛浴 | 乾淨 | 有求 | 必應 | 營主 | 第一次 | 推營 | 海拔 | 營主 | 人超 | 2017 | 10 | 開幕 | 營地 | 超新衛浴 | 乾淨 | 有求 | 必應 | 營主 | 第一次 | 推營 | 海拔 | 500 | 沙坑 | 秋 | 韆 | 適 | 合 | 小朋友"
        },
        {
            "content": "營主非常友善 營位也非常大 不會擁擠  晚上還送拔絲地瓜 好好吃~",
            "type": 2,
            "rating": 5,
            "publishedDate": "2018/01/25",
            "tokenization": "營主 | 友善 | 營位 | 擁擠 | 晚上 | 還送 | 拔絲 | 地瓜 | 好吃"
        },
        {
            "content": "美麗乾淨的露營區。營主用心經營，草皮又大又漂亮，赤腳踩著也舒服。附設沙坑與鞦韆孩子很喜歡，這次遇到營主舉辦搗麻糬活動，驚喜又有趣，是個讓我們下次想再來的營區！",
            "type": 2,
            "rating": 5,
            "publishedDate": "2018/01/18",
            "tokenization": "美麗乾淨 | 露營區 | 營主 | 用心 | 經營 | 草皮 | 漂亮 | 赤腳 | 踩 | 著 | 舒服 | 附設 | 沙坑 | 鞦 | 韆 | 孩子 | 喜歡 | 營主 | 舉辦 | 搗 | 麻 | 糬 | 動 | 驚喜 | 有趣 | 下次 | 想 | 營區"
        },
        {
            "content": "很棒的營地，給的營位很大，草皮非常棒，營主熱情健談，為客人設想週到，是一位很用心經營的營主",
            "type": 2,
            "rating": 5,
            "publishedDate": "2018/01/15",
            "tokenization": "很棒 | 營地 | 給的 | 營位 | 很大 | 草皮 | 棒 | 營主 | 熱情 | 健談 | 為 | 客人 | 設想 | 週到 | 一位 | 用心 | 經營 | 營主"
        },
        {
            "content": "用心經營的好營地。很棒的親子營地，草地維護的很好，空間很大適合小朋友跑跳，一區ㄧ鞦韆和沙坑，小朋友都玩的很開心呢",
            "type": 2,
            "rating": 5,
            "publishedDate": "2018/01/15",
            "tokenization": "用心 | 經營 | 營地 | 很棒 | 親子 | 營地 | 草地 | 維護 | 空間 | 很大 | 適合 | 小朋友 | 跑跳 | 一區 | ㄧ | 鞦 | 韆 | 沙坑 | 小朋友 | 玩 | 開心"
        },
        {
            "content": "營主用心經營，大推~~已經預訂下次再訪時間",
            "type": 2,
            "rating": 5,
            "publishedDate": "2018/01/15",
            "tokenization": "營主 | 用心 | 經營 | 推 | 預訂 | 下次 | 再訪 | 時間"
        },
        {
            "content": "環境整潔舒適，設施完善。",
            "type": 2,
            "rating": 5,
            "publishedDate": "2018/01/13",
            "tokenization": "環境 | 整潔 | 舒適 | 設施 | 完善"
        },
        {
            "content": "風景優美，遊戲設施也讓小朋友玩的非常高興，能感受的出營主用心的經營。",
            "type": 2,
            "rating": 5,
            "publishedDate": "2018/01/07",
            "tokenization": "風景 | 優美 | 遊戲 | 設施 | 小朋友 | 玩 | 感受 | 營主 | 用心 | 經營"
        },
        {
            "content": "很棒的營區，老闆親切，會再去哦～",
            "type": 2,
            "rating": 5,
            "publishedDate": "2017/12/26",
            "tokenization": "很棒 | 營區 | 老闆 | 親切"
        },
        {
            "content": "很用心維護的營區，2017年最舒適的一露，列入再訪名單。",
            "type": 2,
            "rating": 5,
            "publishedDate": "2017/12/25",
            "tokenization": "用心 | 維護 | 營區 | 2017 | 年 | 最舒適 | 一露 | 列入 | 再訪 | 名單"
        },
        {
            "content": "好棒的營地。草皮很漂亮，浴廁很乾淨(老闆娘一個小時清洗一次), 重點是老闆很有心，一直想辦法手做一些設施來增加露友與小朋友的親子關係，也會不定時的辦一些活動讓大家參與哦!雖然是新營區，但老闆與老闆娘及親友相當熱心與親切，好像回到自己家的感覺，優質的營地真心推薦一畝田。",
            "type": 2,
            "rating": 5,
            "publishedDate": "2017/12/24",
            "tokenization": "棒 | 營地 | 草皮 | 很漂亮 | 浴廁 | 乾淨 | 老闆娘 | 小時 | 清洗 | 重點 | 老闆 | 有心 | 想 | 辦法手 | 做 | 設施 | 增加 | 露友 | 小朋友 | 親子關 | 係 | 時 | 辦 | 活動 | 參與 | 新 | 營區 | 老闆 | 老闆娘 | 親友 | 熱心 | 親切 | 好像 | 回到 | 家 | 感覺 | 優質 | 營地 | 真心 | 推薦 | 一畝 | 田"
        },
        {
            "content": "搗麻糬活動很有趣。建議洗手槽上方裝燈，並於水槽就近放置廚餘桶和垃圾桶",
            "type": 2,
            "rating": 4,
            "publishedDate": "2017/12/23",
            "tokenization": "搗 | 麻 | 糬 | 動 | 有趣 | 建議 | 洗手 | 槽 | 上方 | 裝燈 | 水槽 | 就近 | 放置 | 廚餘桶 | 垃圾桶"
        },
        {
            "content": "營位給的很大，分區衛浴、分區的遊戲空間，每區之間不干擾，很喜歡這樣的寧靜。",
            "type": 2,
            "rating": 4,
            "publishedDate": "2017/12/19",
            "tokenization": "營位給 | 很大 | 分區 | 衛浴 | 分區 | 遊戲 | 空間 | 每區 | 之間 | 干擾 | 喜歡 | 寧靜"
        },
        {
            "content": "規劃得很棒～熱水讚！乾淨費心，主人隨時在打掃換垃圾袋～。洗澡水超滿意的～～我跟小孩一起洗都沒冷到！不用叫救援～哈營帳之間給的距離很大～～舒服～老闆在雨中還幫我們一起搭帳～～❤️感恩最難忘搗麻吉活動！Q彈有嚼勁！份量很多～我們全家吃的好開心～「盪鞦韆、沙坑～」放置在沒有車子進出的位置！看得出來規劃得很用心哦～營地乾乾淨淨步行前往蓬萊溪護魚步道很近^_^",
            "type": 2,
            "rating": 5,
            "publishedDate": "2017/12/17",
            "tokenization": "規劃 | 很棒 | 熱 | 水 | 讚 | 乾淨費心 | 主人 | 掃換 | 垃圾袋 | 洗澡水 | 超滿意 | 小孩 | 洗 | 冷到 | 不用 | 救援 | 哈營 | 帳之間給 | 距離 | 很大 | 舒服 | 老闆 | 雨 | 中 | 還幫 | 搭帳 | ❤ | ️ | 感恩 | 最難 | 忘 | 搗 | 麻吉活動 | Q | 彈有 | 嚼 | 勁 | 份量 | 全家 | 吃 | 開心 | 盪 | 鞦 | 韆 | 沙坑 | 放置 | 車子 | 進出 | 位置 | 看得出 | 規劃 | 用心 | 營地 | 乾乾淨淨 | 步行 | 前往 | 蓬萊溪護 | 魚步 | 道"
        },
        {
            "content": "熱情的營主為我們留下深刻的印象！。建議營區內應放置一台飲水機",
            "type": 2,
            "rating": 5,
            "publishedDate": "2017/12/17",
            "tokenization": "熱情 | 營主 | 為 | 留下 | 深刻 | 印象 | 建議 | 營區 | 內應 | 放置 | 一台 | 飲水機"
        },
        {
            "content": "很棒的營地，下次還會再去~",
            "type": 2,
            "rating": 5,
            "publishedDate": "2017/12/13",
            "tokenization": "很棒 | 營地 | 下次 | 還會"
        },
        {
            "content": "小巧而精美。營主相當熱情且親切",
            "type": 2,
            "rating": 5,
            "publishedDate": "2017/12/12",
            "tokenization": "小巧 | 精美 | 營主 | 相當熱 | 情且 | 親切"
        },
        {
            "content": "好營主，環境清幽，晚上睡覺時很寧靜，小孩玩的沙坑鞦韆分散兩處，不會擠在一起。",
            "type": 2,
            "rating": 5,
            "publishedDate": "2017/12/10",
            "tokenization": "營主 | 環境 | 清幽 | 晚上 | 睡覺 | 時 | 很寧靜 | 小孩 | 玩 | 沙坑 | 鞦 | 韆 | 分散 | 兩處 | 擠"
        },
        {
            "content": "草地平整，營主熱情好客，衛浴經常打掃，還有大冰箱可用。",
            "type": 2,
            "rating": 5,
            "publishedDate": "2017/12/10",
            "tokenization": "草地 | 平整 | 營主 | 熱情 | 好客 | 衛浴 | 掃 | 冰箱 | 可用"
        },
        {
            "content": "不錯的營地。可以長期列入親子露營的口袋名單",
            "type": 2,
            "rating": 5,
            "publishedDate": "2017/12/04",
            "tokenization": "不錯 | 營地 | 長 | 期 | 列入 | 親子 | 露營 | 口袋 | 名單"
        },
        {
            "content": "熱心的營主，平坦的場地，超優質草地，能放心放風小孩的優質營區~",
            "type": 2,
            "rating": 5,
            "publishedDate": "2017/12/03",
            "tokenization": "熱心 | 營主 | 平坦 | 場地 | 超優質 | 草地 | 放心 | 放風 | 小孩 | 優質 | 營區"
        },
        {
            "content": "營主很熱心，場地也很優質",
            "type": 2,
            "rating": 5,
            "publishedDate": "2017/12/02",
            "tokenization": "營主 | 很熱心 | 場地 | 優質"
        },
        {
            "content": "環境很清優，真的是可以聽見蟲鳴鳥叫的營地，營地位置還蠻平坦安全很適合孩子，老闆超好的……",
            "type": 2,
            "rating": 5,
            "publishedDate": "2017/11/27",
            "tokenization": "環境 | 清優 | 真的 | 聽見蟲鳴 | 鳥 | 營地 | 營地 | 位置 | 還蠻 | 平坦 | 適合 | 孩子 | 老闆 | 超好"
        }
    ]
}